[{"i":135228,"n":"Álftanes","s":3431,"la":64.1,"lo":-22.0167},{"i":135181,"n":"Garðabær","s":3431,"la":64.0887,"lo":-21.923},{"i":135186,"n":"Hafnarfjörður","s":3431,"la":64.0671,"lo":-21.9377},{"i":135196,"n":"Kjósarhreppur","s":3431,"la":64.3064,"lo":-21.4992},{"i":135197,"n":"Kópavogur","s":3431,"la":64.1123,"lo":-21.913},{"i":135200,"n":"Mosfellsbaer","s":3431,"la":64.15,"lo":-21.65},{"i":135201,"n":"Mosfellsbær","s":3431,"la":64.1667,"lo":-21.7},{"i":135206,"n":"Reykjavík","s":3431,"la":64.1355,"lo":-21.8954},{"i":135211,"n":"Seltjarnarnes","s":3431,"la":64.1531,"lo":-21.995},{"i":135166,"n":"Borgarfjarðarhreppur","s":3433,"la":65.434,"lo":-13.8293},{"i":135168,"n":"Breiðdalshreppur","s":3433,"la":64.8333,"lo":-14.25},{"i":135172,"n":"Egilsstaðir","s":3433,"la":65.2669,"lo":-14.3948},{"i":135173,"n":"Eskifjörður","s":3433,"la":65.0731,"lo":-14.0152},{"i":135177,"n":"Fjarðabyggð","s":3433,"la":65.0833,"lo":-14},{"i":135179,"n":"Fljótsdalshérað","s":3433,"la":65.2502,"lo":-15.3721},{"i":135178,"n":"Fljótsdalshreppur","s":3433,"la":64.8528,"lo":-15.2568},{"i":135191,"n":"Höfn","s":3433,"la":64.2539,"lo":-15.2121},{"i":135203,"n":"Neskaupstaður","s":3433,"la":65.1482,"lo":-13.6837},{"i":135207,"n":"Reyðarfjörður","s":3433,"la":65.0316,"lo":-14.2183},{"i":135163,"n":"Akureyri","s":3437,"la":65.6835,"lo":-18.0878},{"i":135170,"n":"Dalvík","s":3437,"la":65.9702,"lo":-18.5286},{"i":135171,"n":"Dalvíkurbyggð","s":3437,"la":65.8732,"lo":-18.6084},{"i":135175,"n":"Eyjafjarðarsveit","s":3437,"la":65.3333,"lo":-18.1667},{"i":135176,"n":"Fjallabyggð","s":3437,"la":66.0596,"lo":-18.7822},{"i":135185,"n":"Grýtubakkahreppur","s":3437,"la":65.9833,"lo":-18.1167},{"i":135192,"n":"Hörgársveit","s":3437,"la":65.6483,"lo":-18.496},{"i":135194,"n":"Húsavík","s":3437,"la":66.0415,"lo":-17.3383},{"i":135198,"n":"Langanesbyggð","s":3437,"la":66.0519,"lo":-15.1897},{"i":135199,"n":"Laugar","s":3437,"la":65.7216,"lo":-17.3735},{"i":135212,"n":"Siglufjörður","s":3437,"la":66.152,"lo":-18.9081},{"i":135217,"n":"Skútustaðahreppur","s":3437,"la":65.1718,"lo":-16.7789},{"i":135221,"n":"Svalbarðsstrandarhreppur","s":3437,"la":65.7414,"lo":-18.0351},{"i":135223,"n":"Tjörneshreppur","s":3437,"la":66.1167,"lo":-17.2},{"i":135233,"n":"Þingeyjarsveit","s":3437,"la":65.3723,"lo":-17.5993},{"i":135161,"n":"Akrahreppur","s":3435,"la":65.3551,"lo":-18.7957},{"i":135193,"n":"Húnaþing Vestra","s":3435,"la":65.25,"lo":-20.9167},{"i":135209,"n":"Sauðárkrókur","s":3435,"la":65.7461,"lo":-19.6394},{"i":135214,"n":"Skagabyggð","s":3435,"la":65.95,"lo":-20.25},{"i":135222,"n":"Sveitarfélagið Skagafjörður","s":3435,"la":65.5002,"lo":-19.4457},{"i":135182,"n":"Garður","s":3430,"la":64.0656,"lo":-22.6466},{"i":135183,"n":"Grindavík","s":3430,"la":63.8385,"lo":-22.4393},{"i":135195,"n":"Keflavík","s":3430,"la":64.0049,"lo":-22.5624},{"i":135205,"n":"Reykjanesbær","s":3430,"la":63.9981,"lo":-22.5611},{"i":135208,"n":"Sandgerði","s":3430,"la":64.0376,"lo":-22.708},{"i":135227,"n":"Vogar","s":3430,"la":63.9816,"lo":-22.3847},{"i":135229,"n":"Ásahreppur","s":3434,"la":63.8759,"lo":-20.5948},{"i":135164,"n":"Bláskógabyggð","s":3434,"la":64.4167,"lo":-20.3333},{"i":135180,"n":"Flóahreppur","s":3434,"la":63.8957,"lo":-20.8016},{"i":135184,"n":"Grímsnes- og Grafningshreppur","s":3434,"la":64.0853,"lo":-20.9671},{"i":135188,"n":"Hrunamannahreppur","s":3434,"la":64.4094,"lo":-19.7224},{"i":135190,"n":"Hveragerði","s":3434,"la":64.0004,"lo":-21.186},{"i":135202,"n":"Mýrdalshreppur","s":3434,"la":63.5,"lo":-19},{"i":135210,"n":"Selfoss","s":3434,"la":63.9331,"lo":-20.9971},{"i":135213,"n":"Skaftárhreppur","s":3434,"la":63.9595,"lo":-18.1449},{"i":135215,"n":"Skeiða- og Gnúpverjahreppur","s":3434,"la":64.3474,"lo":-19.3776},{"i":135225,"n":"Vestmannaeyjabær","s":3434,"la":63.4388,"lo":-20.269},{"i":135226,"n":"Vestmannaeyjar","s":3434,"la":63.4427,"lo":-20.2734},{"i":135234,"n":"Þorlákshöfn","s":3434,"la":63.8559,"lo":-21.3834},{"i":135162,"n":"Akranes","s":3436,"la":64.3218,"lo":-22.0749},{"i":135165,"n":"Borgarbyggð","s":3436,"la":64.7145,"lo":-21.2379},{"i":135167,"n":"Borgarnes","s":3436,"la":64.5383,"lo":-21.9206},{"i":135169,"n":"Dalabyggð","s":3436,"la":65.1012,"lo":-21.7287},{"i":135174,"n":"Eyja- og Miklaholtshreppur","s":3436,"la":64.8585,"lo":-22.5456},{"i":135187,"n":"Helgafellssveit","s":3436,"la":64.9907,"lo":-22.7895},{"i":135189,"n":"Hvalfjarðarsveit","s":3436,"la":64.4427,"lo":-21.6109},{"i":135232,"n":"Ólafsvík","s":3436,"la":64.8943,"lo":-23.7092},{"i":135216,"n":"Skorradalshreppur","s":3436,"la":64.5167,"lo":-21.5},{"i":135218,"n":"Snæfellsbær","s":3436,"la":64.8667,"lo":-23.5},{"i":135220,"n":"Stykkishólmur","s":3436,"la":65.0754,"lo":-22.7298},{"i":135230,"n":"Ísafjarðarbær","s":3432,"la":66.0759,"lo":-23.1279},{"i":135231,"n":"Ísafjörður","s":3432,"la":66.0747,"lo":-23.135},{"i":135204,"n":"Reykhólahreppur","s":3432,"la":65.6099,"lo":-22.3332},{"i":135219,"n":"Strandabyggð","s":3432,"la":65.7746,"lo":-21.9572},{"i":135224,"n":"Tálknafjarðarhreppur","s":3432,"la":65.6167,"lo":-23.8833}]