[{"i":89736,"n":"Capitán Pablo Lagerenza","s":2785,"la":-19.9167,"lo":-60.7833},{"i":89768,"n":"Fuerte Olimpo","s":2785,"la":-21.0415,"lo":-57.8738},{"i":89743,"n":"Cedrales","s":2784,"la":-25.6567,"lo":-54.7227},{"i":89745,"n":"Ciudad del Este","s":2784,"la":-25.5097,"lo":-54.6111},{"i":89751,"n":"Colonia Minga Porá","s":2784,"la":-24.8667,"lo":-54.9},{"i":89759,"n":"Doctor Juan León Mallorquín","s":2784,"la":-25.4305,"lo":-55.2541},{"i":89782,"n":"Itakyry","s":2784,"la":-24.9861,"lo":-55.1496},{"i":89799,"n":"Naranjal","s":2784,"la":-25.9667,"lo":-55.1833},{"i":89812,"n":"Presidente Franco","s":2784,"la":-25.5638,"lo":-54.611},{"i":89818,"n":"San Alberto","s":2784,"la":-24.9667,"lo":-54.9},{"i":89835,"n":"Santa Rita","s":2784,"la":-25.7833,"lo":-55.0667},{"i":89852,"n":"Yguazú","s":2784,"la":-25.4619,"lo":-55.0001},{"i":89725,"n":"Bella Vista","s":2782,"la":-22.1333,"lo":-56.5167},{"i":89734,"n":"Capitán Bado","s":2782,"la":-23.2667,"lo":-55.5333},{"i":89807,"n":"Pedro Juan Caballero","s":2782,"la":-22.5472,"lo":-55.7333},{"i":89750,"n":"Colonia Menno","s":2780,"la":-22.3667,"lo":-59.8167},{"i":89752,"n":"Colonia Neuland","s":2780,"la":-22.6667,"lo":-60.1167},{"i":89766,"n":"Filadelfia","s":2780,"la":-22.3394,"lo":-60.0316},{"i":89730,"n":"Caaguazú","s":2773,"la":-25.471,"lo":-56.016},{"i":89740,"n":"Carayaó","s":2773,"la":-25.1975,"lo":-56.3988},{"i":89742,"n":"Cecilio Baez","s":2773,"la":-25.0716,"lo":-56.2439},{"i":89748,"n":"Colonia General Alfredo Stroessner","s":2773,"la":-25.3639,"lo":-55.7069},{"i":89757,"n":"Coronel Oviedo","s":2773,"la":-25.4444,"lo":-56.4403},{"i":89760,"n":"Doctor Juan Manuel Frutos","s":2773,"la":-25.3838,"lo":-55.8321},{"i":89796,"n":"Mbutuý","s":2773,"la":-24.9752,"lo":-56.3093},{"i":89816,"n":"Repatriación","s":2773,"la":-25.5333,"lo":-55.95},{"i":89823,"n":"San Joaquín","s":2773,"la":-25.0285,"lo":-56.0428},{"i":89824,"n":"San José","s":2773,"la":-25.5333,"lo":-56.7333},{"i":89853,"n":"Yhú","s":2773,"la":-25.0578,"lo":-55.9227},{"i":89716,"n":"Abaí","s":2775,"la":-26.0333,"lo":-55.9333},{"i":89728,"n":"Buena Vista","s":2775,"la":-26.1839,"lo":-56.0817},{"i":89732,"n":"Caazapá","s":2775,"la":-26.1958,"lo":-56.3681},{"i":89772,"n":"General Higinio Morínigo","s":2775,"la":-25.95,"lo":-55.9167},{"i":89826,"n":"San Juan Nepomuceno","s":2775,"la":-26.1123,"lo":-55.9386},{"i":89850,"n":"Yegros","s":2775,"la":-26.45,"lo":-56.4},{"i":89855,"n":"Yuty","s":2775,"la":-26.6147,"lo":-56.2461},{"i":89747,"n":"Colonia Catuete","s":2771,"la":-24.1333,"lo":-54.6167},{"i":89758,"n":"Corpus Christi","s":2771,"la":-24.0804,"lo":-54.9393},{"i":89790,"n":"La Paloma","s":2771,"la":-24.1296,"lo":-54.6138},{"i":89803,"n":"Nueva Esperanza","s":2771,"la":-24.5076,"lo":-54.8551},{"i":89817,"n":"Salto del Guairá","s":2771,"la":-24.0625,"lo":-54.3069},{"i":89822,"n":"San Isidro de Curuguaty","s":2771,"la":-24.4718,"lo":-55.6923},{"i":89851,"n":"Ygatimi","s":2771,"la":-24.1237,"lo":-55.6442},{"i":89720,"n":"Areguá","s":2777,"la":-25.3125,"lo":-57.3847},{"i":89733,"n":"Capiatá","s":2777,"la":-25.3552,"lo":-57.4455},{"i":89765,"n":"Fernando de la Mora","s":2777,"la":-25.3386,"lo":-57.5217},{"i":89774,"n":"Guarambaré","s":2777,"la":-25.491,"lo":-57.4557},{"i":89786,"n":"Itá","s":2777,"la":-25.5005,"lo":-57.3672},{"i":89784,"n":"Itauguá","s":2777,"la":-25.3926,"lo":-57.3542},{"i":89791,"n":"Lambaré","s":2777,"la":-25.3468,"lo":-57.6065},{"i":89793,"n":"Limpio","s":2777,"la":-25.1661,"lo":-57.4856},{"i":89794,"n":"Mariano Roque Alonso","s":2777,"la":-25.2079,"lo":-57.532},{"i":89802,"n":"Nemby","s":2777,"la":-25.3949,"lo":-57.5357},{"i":89804,"n":"Nueva Italia","s":2777,"la":-25.6108,"lo":-57.4656},{"i":89819,"n":"San Antonio","s":2777,"la":-25.4213,"lo":-57.5472},{"i":89828,"n":"San Lorenzo","s":2777,"la":-25.3397,"lo":-57.5088},{"i":89843,"n":"Villa Elisa","s":2777,"la":-25.3676,"lo":-57.5927},{"i":89854,"n":"Ypacarai","s":2777,"la":-25.4078,"lo":-57.2889},{"i":89726,"n":"Belén","s":2779,"la":-23.4661,"lo":-57.2619},{"i":89755,"n":"Concepción","s":2779,"la":-23.3999,"lo":-57.4324},{"i":89777,"n":"Horqueta","s":2779,"la":-23.3428,"lo":-57.0597},{"i":89718,"n":"Altos","s":2783,"la":-25.2626,"lo":-57.2544},{"i":89722,"n":"Arroyos y Esteros","s":2783,"la":-25.0548,"lo":-57.0987},{"i":89723,"n":"Atyrá","s":2783,"la":-25.2788,"lo":-57.1719},{"i":89729,"n":"Caacupé","s":2783,"la":-25.3858,"lo":-57.1422},{"i":89738,"n":"Caraguatay","s":2783,"la":-25.2384,"lo":-56.8269},{"i":89762,"n":"Emboscada","s":2783,"la":-25.15,"lo":-57.35},{"i":89764,"n":"Eusebio Ayala","s":2783,"la":-25.3828,"lo":-56.9609},{"i":89779,"n":"Isla Pucú","s":2783,"la":-25.3085,"lo":-56.8999},{"i":89780,"n":"Itacurubí de la Cordillera","s":2783,"la":-25.4616,"lo":-56.8533},{"i":89811,"n":"Piribebuy","s":2783,"la":-25.465,"lo":-57.0418},{"i":89820,"n":"San Bernardino","s":2783,"la":-25.3107,"lo":-57.2963},{"i":89833,"n":"Santa Elena","s":2783,"la":-25.4133,"lo":-56.7971},{"i":89840,"n":"Tobatí","s":2783,"la":-25.2611,"lo":-57.0833},{"i":89749,"n":"Colonia Mauricio José Troche","s":2772,"la":-25.5667,"lo":-56.2833},{"i":89756,"n":"Coronel Martínez","s":2772,"la":-25.7586,"lo":-56.6168},{"i":89778,"n":"Independencia","s":2772,"la":-25.691,"lo":-56.2678},{"i":89783,"n":"Itapé","s":2772,"la":-25.8517,"lo":-56.6138},{"i":89785,"n":"Iturbe","s":2772,"la":-26.0551,"lo":-56.4846},{"i":89795,"n":"Mbocayaty","s":2772,"la":-25.7194,"lo":-56.4218},{"i":89800,"n":"Natalicio Talavera","s":2772,"la":-25.6333,"lo":-56.3},{"i":89846,"n":"Villarrica","s":2772,"la":-25.7495,"lo":-56.4352},{"i":89721,"n":"Arquitecto Tomás Romero Pereira","s":2778,"la":-26.4833,"lo":-55.25},{"i":89724,"n":"Bella Vista","s":2778,"la":-27.05,"lo":-55.55},{"i":89735,"n":"Capitán Miranda","s":2778,"la":-27.2,"lo":-55.8},{"i":89741,"n":"Carmen del Paraná","s":2778,"la":-27.2223,"lo":-56.1524},{"i":89746,"n":"Colonia Carlos Antonio López","s":2778,"la":-26.3985,"lo":-54.7569},{"i":89754,"n":"Colonia San Lorenzo","s":2778,"la":-26.4932,"lo":-54.7999},{"i":89761,"n":"Edelira","s":2778,"la":-26.7673,"lo":-55.2787},{"i":89763,"n":"Encarnación","s":2778,"la":-27.3306,"lo":-55.8667},{"i":89767,"n":"Fram","s":2778,"la":-26.9833,"lo":-55.8833},{"i":89769,"n":"General Artigas","s":2778,"la":-26.9352,"lo":-56.2217},{"i":89770,"n":"General Delgado","s":2778,"la":-27.0905,"lo":-56.5247},{"i":89776,"n":"Hohenau","s":2778,"la":-27.0731,"lo":-55.6425},{"i":89787,"n":"Jesús","s":2778,"la":-27.056,"lo":-55.7413},{"i":89801,"n":"Natalio","s":2778,"la":-26.757,"lo":-55.1378},{"i":89805,"n":"Obligado","s":2778,"la":-27.0333,"lo":-55.6333},{"i":89809,"n":"Pirapó","s":2778,"la":-26.8601,"lo":-55.5436},{"i":89813,"n":"Puerto Mayor Otaño","s":2778,"la":-26.4,"lo":-54.7},{"i":89821,"n":"San Cosme y Damián","s":2778,"la":-27.3174,"lo":-56.3309},{"i":89827,"n":"San Juan del Paraná","s":2778,"la":-27.3017,"lo":-55.9651},{"i":89832,"n":"San Pedro del Paraná","s":2778,"la":-26.8327,"lo":-56.2058},{"i":89841,"n":"Trinidad","s":2778,"la":-27.1167,"lo":-55.7833},{"i":89788,"n":"Juan de Ayolas","s":2786,"la":-27.3866,"lo":-56.8472},{"i":89825,"n":"San Juan Bautista","s":2786,"la":-26.6694,"lo":-57.1458},{"i":89829,"n":"San Miguel","s":2786,"la":-26.5,"lo":-57.05},{"i":89830,"n":"San Patricio","s":2786,"la":-26.9667,"lo":-56.8167},{"i":89834,"n":"Santa María","s":2786,"la":-26.7833,"lo":-56.9333},{"i":89836,"n":"Santa Rosa Misiones","s":2786,"la":-26.8873,"lo":-56.849},{"i":89837,"n":"Santiago","s":2786,"la":-27.1431,"lo":-56.768},{"i":89844,"n":"Villa Florida","s":2786,"la":-26.3833,"lo":-57.15},{"i":89744,"n":"Cerrito","s":2781,"la":-27.3422,"lo":-57.6412},{"i":89773,"n":"General José Eduvigis Díaz","s":2781,"la":-27.2014,"lo":-58.3674},{"i":89808,"n":"Pilar","s":2781,"la":-26.8587,"lo":-58.3064},{"i":89717,"n":"Acahay","s":2774,"la":-25.9167,"lo":-57.15},{"i":89731,"n":"Caapucú","s":2774,"la":-26.2352,"lo":-57.1821},{"i":89739,"n":"Carapeguá","s":2774,"la":-25.8,"lo":-57.2333},{"i":89789,"n":"La Colmena","s":2774,"la":-25.8863,"lo":-56.8408},{"i":89797,"n":"Mbuyapey","s":2774,"la":-26.2192,"lo":-56.7578},{"i":89806,"n":"Paraguarí","s":2774,"la":-25.6208,"lo":-57.1472},{"i":89810,"n":"Pirayú","s":2774,"la":-25.4841,"lo":-57.2349},{"i":89815,"n":"Quiindy","s":2774,"la":-25.9761,"lo":-57.2335},{"i":89838,"n":"Sapucaí","s":2774,"la":-25.6665,"lo":-56.9522},{"i":89847,"n":"Yaguarón","s":2774,"la":-25.5614,"lo":-57.2834},{"i":89849,"n":"Ybycuí","s":2774,"la":-26.0167,"lo":-57.05},{"i":89727,"n":"Benjamín Aceval","s":2770,"la":-24.9667,"lo":-57.5667},{"i":89798,"n":"Nanawua","s":2770,"la":-25.2793,"lo":-57.7031},{"i":89845,"n":"Villa Hayes","s":2770,"la":-25.0931,"lo":-57.5236},{"i":89719,"n":"Antequera","s":2776,"la":-24.0853,"lo":-57.2022},{"i":89737,"n":"Capiíbary","s":2776,"la":-24.8,"lo":-56.0333},{"i":89753,"n":"Colonia Nueva Germania","s":2776,"la":-23.9114,"lo":-56.7009},{"i":89771,"n":"General Elizardo Aquino","s":2776,"la":-24.4442,"lo":-56.9006},{"i":89775,"n":"Guayaybi","s":2776,"la":-24.5333,"lo":-56.4333},{"i":89781,"n":"Itacurubí del Rosario","s":2776,"la":-24.5354,"lo":-56.8235},{"i":89792,"n":"Lima","s":2776,"la":-23.8833,"lo":-56.4822},{"i":89814,"n":"Puerto Rosario","s":2776,"la":-24.4413,"lo":-57.1427},{"i":89831,"n":"San Pedro de Ycuamandiyú","s":2776,"la":-24.0853,"lo":-57.0874},{"i":89839,"n":"Tacuatí","s":2776,"la":-23.45,"lo":-56.5833},{"i":89842,"n":"Unión","s":2776,"la":-24.8079,"lo":-56.5215},{"i":89848,"n":"Yataity del Norte","s":2776,"la":-24.8333,"lo":-56.35}]