[{"i":62295,"n":"Aenon Town","s":3753,"la":18.2103,"lo":-77.3985},{"i":62302,"n":"Alley","s":3753,"la":17.7904,"lo":-77.2708},{"i":62307,"n":"Alston","s":3753,"la":18.1764,"lo":-77.4347},{"i":62319,"n":"Ashley","s":3753,"la":18.0144,"lo":-77.3402},{"i":62331,"n":"Banks","s":3753,"la":17.8322,"lo":-77.3073},{"i":62344,"n":"Beckford Kraal","s":3753,"la":18.0855,"lo":-77.324},{"i":62387,"n":"Brandon Hill","s":3753,"la":18.1511,"lo":-77.2366},{"i":62391,"n":"Brixton Hill","s":3753,"la":18.0204,"lo":-77.3174},{"i":62397,"n":"Bucknor","s":3753,"la":18.0062,"lo":-77.2375},{"i":62398,"n":"Bucks Common","s":3753,"la":17.9823,"lo":-77.2385},{"i":62406,"n":"Bushy Park","s":3753,"la":17.9824,"lo":-77.2514},{"i":62446,"n":"Chapelton","s":3753,"la":18.0833,"lo":-77.2667},{"i":62449,"n":"Chateau","s":3753,"la":17.9897,"lo":-77.1874},{"i":62462,"n":"Cockpit","s":3753,"la":17.8887,"lo":-77.1583},{"i":62463,"n":"Coffee Piece","s":3753,"la":18.1383,"lo":-77.4065},{"i":62466,"n":"Colonels Ridge","s":3753,"la":18.1352,"lo":-77.2555},{"i":62485,"n":"Coxswain","s":3753,"la":18.1027,"lo":-77.2344},{"i":62489,"n":"Crofts Hill","s":3753,"la":18.1327,"lo":-77.2051},{"i":62491,"n":"Crooked River","s":3753,"la":18.1429,"lo":-77.3},{"i":62496,"n":"Cumberland","s":3753,"la":18.1052,"lo":-77.4162},{"i":62497,"n":"Curatoe Hill","s":3753,"la":17.9398,"lo":-77.2484},{"i":62504,"n":"Dawkins","s":3753,"la":18.0554,"lo":-77.333},{"i":62533,"n":"Effortville","s":3753,"la":17.9927,"lo":-77.2186},{"i":62565,"n":"Four Paths","s":3753,"la":17.9709,"lo":-77.296},{"i":62566,"n":"Frankfield","s":3753,"la":18.1497,"lo":-77.365},{"i":62570,"n":"Freetown","s":3753,"la":17.9219,"lo":-77.1478},{"i":62585,"n":"Gimme-me-bit","s":3753,"la":17.8895,"lo":-77.2847},{"i":62590,"n":"Glenmuir","s":3753,"la":17.968,"lo":-77.2539},{"i":62602,"n":"Grantham","s":3753,"la":18.1584,"lo":-77.3964},{"i":62606,"n":"Gravel Hill","s":3753,"la":17.9097,"lo":-77.3335},{"i":62638,"n":"Hayes","s":3753,"la":17.8757,"lo":-77.2371},{"i":62640,"n":"Hazard","s":3753,"la":17.9538,"lo":-77.2315},{"i":62661,"n":"Inverness","s":3753,"la":17.912,"lo":-77.1903},{"i":62670,"n":"James Hill","s":3753,"la":18.1875,"lo":-77.337},{"i":62676,"n":"Johns Hall","s":3753,"la":18.1888,"lo":-77.3806},{"i":62683,"n":"Kellits","s":3753,"la":18.1618,"lo":-77.2705},{"i":62712,"n":"Limit","s":3753,"la":18.1529,"lo":-77.4712},{"i":62715,"n":"Lionel Town","s":3753,"la":17.8101,"lo":-77.2406},{"i":62727,"n":"Longville Park","s":3753,"la":17.9119,"lo":-77.1598},{"i":62728,"n":"Longwood","s":3753,"la":17.8075,"lo":-77.2873},{"i":62764,"n":"May Pen","s":3753,"la":17.9645,"lo":-77.2451},{"i":62765,"n":"May Pen Proper","s":3753,"la":17.9703,"lo":-77.2391},{"i":62776,"n":"Milk River","s":3753,"la":17.8756,"lo":-77.3514},{"i":62777,"n":"Mineral Heights","s":3753,"la":17.9418,"lo":-77.2328},{"i":62778,"n":"Mitchell Town","s":3753,"la":17.8128,"lo":-77.2053},{"i":62788,"n":"Moores","s":3753,"la":18.0293,"lo":-77.1854},{"i":62790,"n":"Morgans Forest","s":3753,"la":18.1909,"lo":-77.4102},{"i":62791,"n":"Morgans Pass","s":3753,"la":18.1212,"lo":-77.2749},{"i":62793,"n":"Mount Airy","s":3753,"la":18.0184,"lo":-77.3636},{"i":62812,"n":"New Denbigh","s":3753,"la":17.9856,"lo":-77.271},{"i":62817,"n":"New Longsville","s":3753,"la":18.0307,"lo":-77.2305},{"i":62836,"n":"Old Denbigh","s":3753,"la":17.9612,"lo":-77.267},{"i":62846,"n":"Orange Hill","s":3753,"la":18.1179,"lo":-77.3594},{"i":62847,"n":"Osbourne Store","s":3753,"la":17.9589,"lo":-77.3283},{"i":62848,"n":"Paisley","s":3753,"la":17.9629,"lo":-77.2237},{"i":62849,"n":"Palmers Cross","s":3753,"la":17.95,"lo":-77.2034},{"i":62858,"n":"Part of Banana Ground","s":3753,"la":18.0802,"lo":-77.4097},{"i":62859,"n":"Part of Douglas Castle","s":3753,"la":18.187,"lo":-77.2754},{"i":62861,"n":"Part of Kellits","s":3753,"la":18.1716,"lo":-77.2512},{"i":62871,"n":"Peckham","s":3753,"la":18.1715,"lo":-77.3977},{"i":62875,"n":"Pennants","s":3753,"la":18.1103,"lo":-77.3131},{"i":62886,"n":"Pleasant Valley","s":3753,"la":18.011,"lo":-77.2903},{"i":62897,"n":"Portland Cottage","s":3753,"la":17.7462,"lo":-77.1877},{"i":62901,"n":"Porus","s":3753,"la":18.052,"lo":-77.4001},{"i":62910,"n":"Race Course","s":3753,"la":17.8402,"lo":-77.2822},{"i":62930,"n":"Richmond Park","s":3753,"la":18.0517,"lo":-77.3764},{"i":62934,"n":"Ritchies","s":3753,"la":18.139,"lo":-77.4289},{"i":62942,"n":"Rock","s":3753,"la":17.9912,"lo":-77.337},{"i":62944,"n":"Rock River","s":3753,"la":18.0655,"lo":-77.1971},{"i":62946,"n":"Rocky Point","s":3753,"la":17.7769,"lo":-77.2482},{"i":62964,"n":"Salt River","s":3753,"la":17.8414,"lo":-77.1741},{"i":62969,"n":"Sandy Bay","s":3753,"la":17.951,"lo":-77.1623},{"i":62970,"n":"Sanguinetti","s":3753,"la":18.1559,"lo":-77.4294},{"i":62984,"n":"Sedgepond","s":3753,"la":17.8475,"lo":-77.3264},{"i":62992,"n":"Silent Hill","s":3753,"la":18.1915,"lo":-77.4592},{"i":62998,"n":"Smithville","s":3753,"la":18.1198,"lo":-77.3856},{"i":63006,"n":"Spaldings","s":3753,"la":18.1687,"lo":-77.458},{"i":63040,"n":"Summerfield","s":3753,"la":18.0943,"lo":-77.2843},{"i":63048,"n":"Thompson Town","s":3753,"la":18.0897,"lo":-77.3719},{"i":63053,"n":"Tollgate","s":3753,"la":17.9719,"lo":-77.3657},{"i":63061,"n":"Treadlight","s":3753,"la":17.9926,"lo":-77.2553},{"i":63067,"n":"Trout Hall","s":3753,"la":18.1378,"lo":-77.333},{"i":63071,"n":"Turners","s":3753,"la":18.0665,"lo":-77.2352},{"i":63087,"n":"Water Lane","s":3753,"la":17.8245,"lo":-77.2595},{"i":63119,"n":"Woodhall","s":3753,"la":18.0476,"lo":-77.2758},{"i":63127,"n":"York Town","s":3753,"la":17.9251,"lo":-77.3},{"i":62322,"n":"Askenish","s":3749,"la":18.3849,"lo":-78.1491},{"i":62409,"n":"Cacoon","s":3749,"la":18.4164,"lo":-78.2073},{"i":62410,"n":"Cacoon Castle","s":3749,"la":18.4025,"lo":-78.0134},{"i":62422,"n":"Cascade","s":3749,"la":18.3975,"lo":-78.1034},{"i":62425,"n":"Cash Hill","s":3749,"la":18.3692,"lo":-78.1094},{"i":62432,"n":"Cauldwell","s":3749,"la":18.3858,"lo":-78.2411},{"i":62443,"n":"Chambers Pen","s":3749,"la":18.4052,"lo":-78.1598},{"i":62452,"n":"Chester Castle","s":3749,"la":18.3382,"lo":-77.9472},{"i":62479,"n":"Copse","s":3749,"la":18.3947,"lo":-77.9768},{"i":62484,"n":"Cousins Cove","s":3749,"la":18.4243,"lo":-78.2375},{"i":62512,"n":"Dias","s":3749,"la":18.3938,"lo":-78.1856},{"i":62608,"n":"Great Valley","s":3749,"la":18.4117,"lo":-78.0502},{"i":62610,"n":"Green Island","s":3749,"la":18.384,"lo":-78.2702},{"i":62620,"n":"Haddington","s":3749,"la":18.4204,"lo":-78.0038},{"i":62657,"n":"Hopewell","s":3749,"la":18.4432,"lo":-78.0264},{"i":62672,"n":"Jericho","s":3749,"la":18.4374,"lo":-78.1303},{"i":62685,"n":"Kendal","s":3749,"la":18.3629,"lo":-78.2272},{"i":62693,"n":"Kingsvale","s":3749,"la":18.3809,"lo":-78.2052},{"i":62702,"n":"Lances Bay","s":3749,"la":18.4382,"lo":-78.2144},{"i":62723,"n":"Logwood","s":3749,"la":18.3488,"lo":-78.2962},{"i":62731,"n":"Lucea","s":3749,"la":18.4509,"lo":-78.1736},{"i":62732,"n":"Lucea East","s":3749,"la":18.422,"lo":-78.1667},{"i":62733,"n":"Lucea West","s":3749,"la":18.4424,"lo":-78.1866},{"i":62752,"n":"March Town","s":3749,"la":18.3295,"lo":-78.2766},{"i":62758,"n":"Maryland","s":3749,"la":18.3868,"lo":-78.1282},{"i":62799,"n":"Mount Peto","s":3749,"la":18.3575,"lo":-78.0229},{"i":62844,"n":"Orange Bay","s":3749,"la":18.3427,"lo":-78.32},{"i":62873,"n":"Pell River","s":3749,"la":18.3789,"lo":-78.219},{"i":62890,"n":"Pondside","s":3749,"la":18.4022,"lo":-78.0734},{"i":62913,"n":"Ramble","s":3749,"la":18.3467,"lo":-77.988},{"i":62945,"n":"Rock Spring","s":3749,"la":18.348,"lo":-78.2439},{"i":62968,"n":"Sandy Bay","s":3749,"la":18.4375,"lo":-78.0838},{"i":62972,"n":"Santoy","s":3749,"la":18.3588,"lo":-78.2839},{"i":63038,"n":"Success","s":3749,"la":18.3773,"lo":-78.0511},{"i":63120,"n":"Woodlands","s":3749,"la":18.4456,"lo":-77.9996},{"i":63123,"n":"Woodsville","s":3749,"la":18.3695,"lo":-78.0722},{"i":62305,"n":"Allman Town","s":3748,"la":17.983,"lo":-76.7869},{"i":62380,"n":"Bournemouth Gardens","s":3748,"la":17.9701,"lo":-76.7627},{"i":62416,"n":"Campbell Town","s":3748,"la":17.9791,"lo":-76.7813},{"i":62439,"n":"Central Down Town","s":3748,"la":17.9696,"lo":-76.7926},{"i":62498,"n":"D'Aguilar Town/ Rennock Lodge","s":3748,"la":17.97,"lo":-76.737},{"i":62509,"n":"Denham Town","s":3748,"la":17.9781,"lo":-76.7998},{"i":62530,"n":"East Down Town","s":3748,"la":17.972,"lo":-76.7847},{"i":62558,"n":"Fletchers Land","s":3748,"la":17.9797,"lo":-76.791},{"i":62567,"n":"Franklyn Town","s":3748,"la":17.9779,"lo":-76.7734},{"i":62629,"n":"Hannah Town/ Craig Town","s":3748,"la":17.98,"lo":-76.7943},{"i":62679,"n":"Johnson Town","s":3748,"la":17.9777,"lo":-76.7559},{"i":62691,"n":"Kingston","s":3748,"la":17.997,"lo":-76.7936},{"i":62692,"n":"Kingston Gardens","s":3748,"la":17.9784,"lo":-76.7868},{"i":62748,"n":"Manley Meadows","s":3748,"la":17.9691,"lo":-76.7712},{"i":62825,"n":"Newport East","s":3748,"la":17.9742,"lo":-76.8066},{"i":62827,"n":"Newton Square","s":3748,"la":17.9735,"lo":-76.7721},{"i":62831,"n":"Norman Gardens","s":3748,"la":17.978,"lo":-76.7594},{"i":62866,"n":"Passmore Town","s":3748,"la":17.973,"lo":-76.7765},{"i":62895,"n":"Port Royal","s":3748,"la":17.9374,"lo":-76.8406},{"i":62911,"n":"Rae Town","s":3748,"la":17.9677,"lo":-76.7797},{"i":62949,"n":"Rollington Town","s":3748,"la":17.9769,"lo":-76.7652},{"i":63005,"n":"Southside","s":3748,"la":17.9657,"lo":-76.7862},{"i":63016,"n":"Springfield","s":3748,"la":17.9712,"lo":-76.7561},{"i":63052,"n":"Tivoli Gardens","s":3748,"la":17.9733,"lo":-76.8009},{"i":63096,"n":"West Down Town","s":3748,"la":17.9729,"lo":-76.797},{"i":62304,"n":"Alligator Pond","s":3754,"la":17.8837,"lo":-77.5607},{"i":62321,"n":"Asia/Pratville","s":3754,"la":17.9158,"lo":-77.4156},{"i":62323,"n":"Auchtembeddie","s":3754,"la":18.2254,"lo":-77.6036},{"i":62349,"n":"Bellefield","s":3754,"la":18.0927,"lo":-77.44},{"i":62354,"n":"Bethany","s":3754,"la":18.1537,"lo":-77.5503},{"i":62366,"n":"Blue Mountain","s":3754,"la":18.0709,"lo":-77.4284},{"i":62374,"n":"Bombay","s":3754,"la":18.1178,"lo":-77.4494},{"i":62407,"n":"Butt-Up","s":3754,"la":17.9731,"lo":-77.5778},{"i":62437,"n":"Cedar Grove","s":3754,"la":18.0123,"lo":-77.4963},{"i":62444,"n":"Chantilly","s":3754,"la":18.1045,"lo":-77.4663},{"i":62453,"n":"Christiana","s":3754,"la":18.1802,"lo":-77.4904},{"i":62454,"n":"Chudleigh","s":3754,"la":18.1515,"lo":-77.5071},{"i":62460,"n":"Cobbla","s":3754,"la":18.1406,"lo":-77.47},{"i":62465,"n":"Coleyville","s":3754,"la":18.1999,"lo":-77.5192},{"i":62467,"n":"Comfort","s":3754,"la":18.0539,"lo":-77.4248},{"i":62470,"n":"Comfort Hall","s":3754,"la":18.1879,"lo":-77.6104},{"i":62474,"n":"Content","s":3754,"la":18.0744,"lo":-77.4512},{"i":62486,"n":"Craig Head","s":3754,"la":18.2366,"lo":-77.563},{"i":62492,"n":"Cross Keys","s":3754,"la":17.9073,"lo":-77.5011},{"i":62510,"n":"Devon","s":3754,"la":18.1659,"lo":-77.5251},{"i":62517,"n":"Downs","s":3754,"la":17.95,"lo":-77.5731},{"i":62536,"n":"Ellen Street","s":3754,"la":17.968,"lo":-77.4393},{"i":62543,"n":"Evergreen","s":3754,"la":18.151,"lo":-77.5996},{"i":62547,"n":"Fairfield","s":3754,"la":18.0312,"lo":-77.5754},{"i":62571,"n":"French Park","s":3754,"la":17.9557,"lo":-77.5447},{"i":62581,"n":"George's Valley","s":3754,"la":18.0317,"lo":-77.4808},{"i":62595,"n":"Good Intent","s":3754,"la":18.2081,"lo":-77.5709},{"i":62613,"n":"Greenvale","s":3754,"la":18.0393,"lo":-77.5324},{"i":62617,"n":"Grove Place","s":3754,"la":18.1047,"lo":-77.5292},{"i":62618,"n":"Grove Town","s":3754,"la":17.8861,"lo":-77.4588},{"i":62633,"n":"Harmons","s":3754,"la":17.9817,"lo":-77.4121},{"i":62635,"n":"Harry Watch","s":3754,"la":18.1731,"lo":-77.5761},{"i":62636,"n":"Hatfield","s":3754,"la":18.0156,"lo":-77.5401},{"i":62641,"n":"Heartease","s":3754,"la":18.0488,"lo":-77.4824},{"i":62646,"n":"Hibernia","s":3754,"la":18.1758,"lo":-77.5483},{"i":62659,"n":"Huntley","s":3754,"la":18.0665,"lo":-77.5817},{"i":62686,"n":"Kendal","s":3754,"la":18.0832,"lo":-77.5032},{"i":62697,"n":"Knockpatrick","s":3754,"la":17.9903,"lo":-77.4927},{"i":62701,"n":"Lancaster","s":3754,"la":17.936,"lo":-77.4613},{"i":62716,"n":"Litchfield","s":3754,"la":18.135,"lo":-77.5245},{"i":62740,"n":"Maidstone","s":3754,"la":18.1016,"lo":-77.5728},{"i":62745,"n":"Mandeville","s":3754,"la":18.0417,"lo":-77.5071},{"i":62746,"n":"Mandeville Proper","s":3754,"la":18.0445,"lo":-77.5057},{"i":62753,"n":"Marlie Hill","s":3754,"la":17.8669,"lo":-77.5083},{"i":62763,"n":"May Day","s":3754,"la":18.0095,"lo":-77.4761},{"i":62769,"n":"Medina","s":3754,"la":18.1224,"lo":-77.5964},{"i":62773,"n":"Mike Town","s":3754,"la":18.0425,"lo":-77.5549},{"i":62775,"n":"Mile Gully","s":3754,"la":18.1339,"lo":-77.5656},{"i":62813,"n":"New Forest","s":3754,"la":17.9201,"lo":-77.5587},{"i":62814,"n":"New Green","s":3754,"la":18.0766,"lo":-77.5257},{"i":62824,"n":"Newport","s":3754,"la":17.9629,"lo":-77.5049},{"i":62837,"n":"Old England","s":3754,"la":17.985,"lo":-77.4602},{"i":62856,"n":"Part Of Banana Ground","s":3754,"la":18.0791,"lo":-77.4213},{"i":62857,"n":"Part Of Gutters","s":3754,"la":18.0064,"lo":-77.579},{"i":62864,"n":"Part of Spaldings","s":3754,"la":18.1582,"lo":-77.4663},{"i":62882,"n":"Pike","s":3754,"la":18.2323,"lo":-77.5379},{"i":62887,"n":"Plowden","s":3754,"la":17.8918,"lo":-77.5385},{"i":62900,"n":"Porus","s":3754,"la":18.0354,"lo":-77.4117},{"i":62905,"n":"Prospect","s":3754,"la":17.9824,"lo":-77.5678},{"i":62929,"n":"Richmond","s":3754,"la":18.0256,"lo":-77.4634},{"i":62941,"n":"Robins Hall","s":3754,"la":18.204,"lo":-77.5501},{"i":62953,"n":"Rose Hill","s":3754,"la":17.9247,"lo":-77.5234},{"i":62958,"n":"Royal Flat","s":3754,"la":18.0496,"lo":-77.4683},{"i":62978,"n":"Scotts Pass","s":3754,"la":17.9992,"lo":-77.3982},{"i":63000,"n":"Snowdon","s":3754,"la":17.942,"lo":-77.4914},{"i":63002,"n":"Somerset","s":3754,"la":18.0804,"lo":-77.5431},{"i":63014,"n":"Spring Ground","s":3754,"la":18.1623,"lo":-77.4798},{"i":63018,"n":"Spur Tree","s":3754,"la":18.0065,"lo":-77.5566},{"i":63025,"n":"St. Paul's","s":3754,"la":18.1314,"lo":-77.612},{"i":63043,"n":"Swaby's Hope","s":3754,"la":17.9861,"lo":-77.5333},{"i":63055,"n":"Top Hill","s":3754,"la":18.1162,"lo":-77.5034},{"i":63076,"n":"Victoria Town","s":3754,"la":17.9047,"lo":-77.3779},{"i":63080,"n":"Walderston","s":3754,"la":18.1164,"lo":-77.4861},{"i":63092,"n":"Watham","s":3754,"la":18.0068,"lo":-77.5187},{"i":63107,"n":"Williamsfield","s":3754,"la":18.0666,"lo":-77.4658},{"i":62327,"n":"Balcarres","s":3752,"la":18.1673,"lo":-76.7206},{"i":62330,"n":"Bangor Ridge","s":3752,"la":18.1364,"lo":-76.689},{"i":62351,"n":"Belvedere","s":3752,"la":18.2077,"lo":-76.6967},{"i":62362,"n":"Black Hill","s":3752,"la":18.2179,"lo":-76.5976},{"i":62378,"n":"Boundbrook","s":3752,"la":18.1757,"lo":-76.4708},{"i":62388,"n":"Breastworks","s":3752,"la":18.16,"lo":-76.4661},{"i":62399,"n":"Buff Bay","s":3752,"la":18.2329,"lo":-76.6612},{"i":62408,"n":"Bybrook","s":3752,"la":18.1464,"lo":-76.6573},{"i":62423,"n":"Cascade","s":3752,"la":18.0938,"lo":-76.7122},{"i":62427,"n":"Castle Comfort","s":3752,"la":18.1422,"lo":-76.3463},{"i":62440,"n":"Central Port Antonio","s":3752,"la":18.1876,"lo":-76.4534},{"i":62447,"n":"Charles Town","s":3752,"la":18.2053,"lo":-76.6639},{"i":62458,"n":"Claverty Cottage","s":3752,"la":18.1488,"lo":-76.6392},{"i":62468,"n":"Comfort Castle","s":3752,"la":18.0483,"lo":-76.4161},{"i":62518,"n":"Drapers","s":3752,"la":18.1712,"lo":-76.4061},{"i":62528,"n":"Durham","s":3752,"la":18.0857,"lo":-76.5156},{"i":62548,"n":"Fairy Hill","s":3752,"la":18.1651,"lo":-76.3659},{"i":62552,"n":"Fellowship","s":3752,"la":18.1278,"lo":-76.472},{"i":62575,"n":"Fruitfulvale","s":3752,"la":18.1089,"lo":-76.5862},{"i":62642,"n":"Hectors River","s":3752,"la":18.0009,"lo":-76.2706},{"i":62652,"n":"Hope Bay","s":3752,"la":18.1875,"lo":-76.5758},{"i":62687,"n":"Kensington","s":3752,"la":18.0677,"lo":-76.3005},{"i":62724,"n":"Long Bay","s":3752,"la":18.0858,"lo":-76.3251},{"i":62726,"n":"Long Road","s":3752,"la":18.0086,"lo":-76.2948},{"i":62744,"n":"Manchioneal","s":3752,"la":18.0444,"lo":-76.2773},{"i":62787,"n":"Moore Town","s":3752,"la":18.0777,"lo":-76.4258},{"i":62800,"n":"Mount Pleasant","s":3752,"la":18.1633,"lo":-76.5047},{"i":62829,"n":"Nonsuch","s":3752,"la":18.1382,"lo":-76.4047},{"i":62832,"n":"Norwich","s":3752,"la":18.1882,"lo":-76.4771},{"i":62843,"n":"Orange Bay","s":3752,"la":18.2031,"lo":-76.6225},{"i":62892,"n":"Port Antonio","s":3752,"la":18.1761,"lo":-76.4509},{"i":62904,"n":"Prospect","s":3752,"la":18.1748,"lo":-76.4355},{"i":62943,"n":"Rock Hall","s":3752,"la":18.1617,"lo":-76.5305},{"i":62989,"n":"Sherwood Forest","s":3752,"la":18.1543,"lo":-76.3782},{"i":62990,"n":"Shirley Castle","s":3752,"la":18.1566,"lo":-76.6111},{"i":62994,"n":"Skibo","s":3752,"la":18.1732,"lo":-76.6275},{"i":62999,"n":"Snow Hill","s":3752,"la":18.1947,"lo":-76.4935},{"i":63015,"n":"Spring Hill","s":3752,"la":18.1259,"lo":-76.7291},{"i":63024,"n":"St. Margaret's Bay","s":3752,"la":18.1908,"lo":-76.5289},{"i":63045,"n":"Swift River","s":3752,"la":18.1577,"lo":-76.5787},{"i":63060,"n":"Tranquility","s":3752,"la":18.1803,"lo":-76.6815},{"i":63113,"n":"Windsor","s":3752,"la":18.1067,"lo":-76.4463},{"i":63114,"n":"Windsor Castle","s":3752,"la":18.2489,"lo":-76.6903},{"i":63115,"n":"Windsor Forest","s":3752,"la":18.1206,"lo":-76.3388},{"i":62316,"n":"Arcadia","s":3751,"la":18.0374,"lo":-76.782},{"i":62317,"n":"Arlene Gardens","s":3751,"la":18.0371,"lo":-76.8179},{"i":62318,"n":"Arnett Gardens","s":3751,"la":17.9915,"lo":-76.7983},{"i":62324,"n":"August Town","s":3751,"la":17.9956,"lo":-76.7367},{"i":62334,"n":"Barbican","s":3751,"la":18.0355,"lo":-76.7699},{"i":62357,"n":"Beverley Hills","s":3751,"la":18.0083,"lo":-76.7621},{"i":62361,"n":"Bito","s":3751,"la":17.9736,"lo":-76.6663},{"i":62365,"n":"Bloxborough","s":3751,"la":17.9958,"lo":-76.6477},{"i":62377,"n":"Boucher Park","s":3751,"la":18.0034,"lo":-76.8126},{"i":62385,"n":"Brandon Hill","s":3751,"la":18.1482,"lo":-76.8051},{"i":62400,"n":"Bull Bay/ Seven Mile","s":3751,"la":17.9525,"lo":-76.684},{"i":62417,"n":"Cane River","s":3751,"la":17.981,"lo":-76.6862},{"i":62426,"n":"Cassia Park","s":3751,"la":18.0205,"lo":-76.8067},{"i":62433,"n":"Cavaliers","s":3751,"la":18.0968,"lo":-76.8432},{"i":62450,"n":"Cherry Gardens","s":3751,"la":18.0496,"lo":-76.7787},{"i":62461,"n":"Cockburn Gardens","s":3751,"la":18.0036,"lo":-76.8243},{"i":62471,"n":"Constant Spring","s":3751,"la":18.0508,"lo":-76.7937},{"i":62472,"n":"Constant Spring Gardens","s":3751,"la":18.0294,"lo":-76.7996},{"i":62473,"n":"Constitution Hill","s":3751,"la":18.0149,"lo":-76.7052},{"i":62476,"n":"Content Gap","s":3751,"la":18.0408,"lo":-76.6907},{"i":62478,"n":"Cooreville Gardens","s":3751,"la":18.0224,"lo":-76.8485},{"i":62493,"n":"Cross Roads","s":3751,"la":17.9945,"lo":-76.7881},{"i":62499,"n":"Dallas","s":3751,"la":17.9846,"lo":-76.7126},{"i":62506,"n":"Delacree Park/ Union Gardens","s":3751,"la":17.9921,"lo":-76.8224},{"i":62507,"n":"Delacree Pen","s":3751,"la":17.9958,"lo":-76.8171},{"i":62519,"n":"Drewsland","s":3751,"la":18.0238,"lo":-76.8263},{"i":62520,"n":"Drumblair","s":3751,"la":18.0235,"lo":-76.7876},{"i":62523,"n":"Duhaney Park","s":3751,"la":18.0309,"lo":-76.8462},{"i":62531,"n":"Eastwood Park Gardens","s":3751,"la":18.0189,"lo":-76.8007},{"i":62537,"n":"Elleston Flats/ Mona Commons","s":3751,"la":18.0095,"lo":-76.7403},{"i":62554,"n":"Ferry","s":3751,"la":18.0277,"lo":-76.8672},{"i":62562,"n":"Forest Hills Gardens","s":3751,"la":18.0385,"lo":-76.8287},{"i":62563,"n":"Forest Hills/ Plantation Height","s":3751,"la":18.043,"lo":-76.8514},{"i":62594,"n":"Golden Spring","s":3751,"la":18.0945,"lo":-76.7973},{"i":62598,"n":"Gordon Town","s":3751,"la":18.0376,"lo":-76.7235},{"i":62603,"n":"Grants Pen","s":3751,"la":18.0326,"lo":-76.7889},{"i":62614,"n":"Greenwich Town/ Newport West","s":3751,"la":17.9844,"lo":-76.8256},{"i":62623,"n":"Half Way Tree","s":3751,"la":18.0125,"lo":-76.7993},{"i":62624,"n":"Half-Way-Tree","s":3751,"la":18.0126,"lo":-76.7958},{"i":62630,"n":"Harbour View","s":3751,"la":17.9515,"lo":-76.7166},{"i":62637,"n":"Havendale","s":3751,"la":18.0543,"lo":-76.8087},{"i":62644,"n":"Hermitage","s":3751,"la":17.9835,"lo":-76.741},{"i":62653,"n":"Hope Pastures/ UTECH","s":3751,"la":18.0231,"lo":-76.7499},{"i":62654,"n":"Hope Tavern","s":3751,"la":18.0123,"lo":-76.732},{"i":62658,"n":"Hughenden","s":3751,"la":18.0304,"lo":-76.8173},{"i":62663,"n":"Irish Town","s":3751,"la":18.0623,"lo":-76.7026},{"i":62667,"n":"Jacks Hill","s":3751,"la":18.0387,"lo":-76.7489},{"i":62681,"n":"Jones Town","s":3751,"la":17.9842,"lo":-76.7969},{"i":62684,"n":"Kencot","s":3751,"la":18.0004,"lo":-76.7983},{"i":62695,"n":"Kintyre","s":3751,"la":18.0213,"lo":-76.7269},{"i":62703,"n":"Lawrence Tavern","s":3751,"la":18.1374,"lo":-76.8474},{"i":62708,"n":"Liguanea","s":3751,"la":18.021,"lo":-76.7683},{"i":62741,"n":"Majestic Gardens","s":3751,"la":18.0002,"lo":-76.8329},{"i":62749,"n":"Mannings Hill","s":3751,"la":18.0705,"lo":-76.8129},{"i":62750,"n":"Mannings Hill (Rural)","s":3751,"la":18.0817,"lo":-76.8233},{"i":62757,"n":"Marverley","s":3751,"la":18.0268,"lo":-76.8265},{"i":62759,"n":"Maryland","s":3751,"la":18.0517,"lo":-76.7432},{"i":62761,"n":"Mavis Bank","s":3751,"la":18.0333,"lo":-76.6667},{"i":62762,"n":"Maxfield Park","s":3751,"la":17.9994,"lo":-76.808},{"i":62766,"n":"Meadowbrook","s":3751,"la":18.0471,"lo":-76.8155},{"i":62767,"n":"Meadowbrook Estate","s":3751,"la":18.0374,"lo":-76.8296},{"i":62780,"n":"Molynes Four Roads","s":3751,"la":18.0103,"lo":-76.8111},{"i":62781,"n":"Molynes Gardens","s":3751,"la":18.0198,"lo":-76.8162},{"i":62782,"n":"Mona Heights","s":3751,"la":18.0133,"lo":-76.7509},{"i":62796,"n":"Mount James","s":3751,"la":18.1207,"lo":-76.7739},{"i":62804,"n":"Mountain View Gardens","s":3751,"la":17.9919,"lo":-76.7607},{"i":62810,"n":"Nannyville","s":3751,"la":17.9968,"lo":-76.7695},{"i":62815,"n":"New Haven","s":3751,"la":18.0295,"lo":-76.8542},{"i":62816,"n":"New Kingston","s":3751,"la":18.0075,"lo":-76.7832},{"i":62830,"n":"Norbrook","s":3751,"la":18.0548,"lo":-76.785},{"i":62834,"n":"Oaklands","s":3751,"la":18.0356,"lo":-76.7956},{"i":62851,"n":"Papine","s":3751,"la":18.0154,"lo":-76.7387},{"i":62853,"n":"Parks Road","s":3751,"la":18.098,"lo":-76.8594},{"i":62867,"n":"Patrick City","s":3751,"la":18.0318,"lo":-76.8377},{"i":62874,"n":"Pembroke Hall","s":3751,"la":18.0311,"lo":-76.83},{"i":62876,"n":"Penwood","s":3751,"la":18.0195,"lo":-76.8309},{"i":62908,"n":"Queensborough/ Tunbridge","s":3751,"la":18.0429,"lo":-76.8212},{"i":62917,"n":"Red Hills (Rural)","s":3751,"la":18.0678,"lo":-76.8609},{"i":62918,"n":"Red Hills Gardens","s":3751,"la":18.03,"lo":-76.8099},{"i":62919,"n":"Red Hills/ Sterling Castle","s":3751,"la":18.0595,"lo":-76.8403},{"i":62931,"n":"Richmond Park","s":3751,"la":18.0056,"lo":-76.8046},{"i":62938,"n":"Riverton City","s":3751,"la":18.0144,"lo":-76.849},{"i":62947,"n":"Roehampton","s":3751,"la":18.0432,"lo":-76.8084},{"i":62955,"n":"Rose Town","s":3751,"la":17.987,"lo":-76.8073},{"i":62982,"n":"Seaview Gardens","s":3751,"la":18.0062,"lo":-76.8411},{"i":62983,"n":"Seaward Pen","s":3751,"la":18.019,"lo":-76.8237},{"i":62986,"n":"Seymour Lands","s":3751,"la":18.0129,"lo":-76.7771},{"i":63026,"n":"St. Peter's","s":3751,"la":18.0788,"lo":-76.672},{"i":63028,"n":"Stadium Gardens","s":3751,"la":17.995,"lo":-76.7764},{"i":63033,"n":"Stony Hill","s":3751,"la":18.0792,"lo":-76.7847},{"i":63044,"n":"Swallowfield","s":3751,"la":18.0049,"lo":-76.7744},{"i":63047,"n":"Temple Hall","s":3751,"la":18.1047,"lo":-76.8182},{"i":63051,"n":"Three Oaks/ Glendale","s":3751,"la":18.0313,"lo":-76.8245},{"i":63056,"n":"Tower Hill","s":3751,"la":18.0118,"lo":-76.8281},{"i":63059,"n":"Trafalgar Park","s":3751,"la":18.0128,"lo":-76.7846},{"i":63063,"n":"Trench Town","s":3751,"la":17.9874,"lo":-76.8012},{"i":63074,"n":"University","s":3751,"la":18.0009,"lo":-76.7477},{"i":63077,"n":"Vineyard Town","s":3751,"la":17.9869,"lo":-76.7706},{"i":63082,"n":"Waltham Gardens","s":3751,"la":18.0109,"lo":-76.8205},{"i":63085,"n":"Washington Gardens","s":3751,"la":18.0217,"lo":-76.8402},{"i":63090,"n":"Waterhouse","s":3751,"la":18.0123,"lo":-76.835},{"i":63102,"n":"Whitehall","s":3751,"la":18.0384,"lo":-76.8058},{"i":63104,"n":"Whitfield Town","s":3751,"la":17.9921,"lo":-76.8091},{"i":63111,"n":"Wilton Gardens/ Rema","s":3751,"la":17.9829,"lo":-76.8042},{"i":63117,"n":"Woodford","s":3751,"la":18.0736,"lo":-76.7463},{"i":63118,"n":"Woodford Park","s":3751,"la":17.9871,"lo":-76.7812},{"i":63128,"n":"Zaidie Gardens","s":3751,"la":18.0257,"lo":-76.8098},{"i":62291,"n":"Aboukir","s":3744,"la":18.2509,"lo":-77.3433},{"i":62300,"n":"Alderton","s":3744,"la":18.2871,"lo":-77.2083},{"i":62301,"n":"Alexandria","s":3744,"la":18.3041,"lo":-77.3531},{"i":62308,"n":"Alva","s":3744,"la":18.2968,"lo":-77.3172},{"i":62329,"n":"Bamboo","s":3744,"la":18.3922,"lo":-77.2643},{"i":62345,"n":"Beecher Town","s":3744,"la":18.3847,"lo":-77.1162},{"i":62352,"n":"Bensonton","s":3744,"la":18.2232,"lo":-77.2086},{"i":62364,"n":"Blackstonedge","s":3744,"la":18.2736,"lo":-77.0425},{"i":62373,"n":"Bohemia","s":3744,"la":18.2124,"lo":-77.4695},{"i":62376,"n":"Borobridge","s":3744,"la":18.1978,"lo":-77.4275},{"i":62396,"n":"Browns Town","s":3744,"la":18.3846,"lo":-77.3529},{"i":62412,"n":"Calderwood","s":3744,"la":18.2564,"lo":-77.2714},{"i":62424,"n":"Cascade","s":3744,"la":18.2321,"lo":-77.4625},{"i":62435,"n":"Cave Valley","s":3744,"la":18.2327,"lo":-77.3634},{"i":62442,"n":"Chalky Hill","s":3744,"la":18.3796,"lo":-77.1752},{"i":62451,"n":"Chester","s":3744,"la":18.4479,"lo":-77.265},{"i":62456,"n":"Claremont","s":3744,"la":18.3256,"lo":-77.2064},{"i":62464,"n":"Cole Gate","s":3744,"la":18.3797,"lo":-77.0852},{"i":62477,"n":"Content Garden","s":3744,"la":18.4098,"lo":-77.0754},{"i":62494,"n":"Cuffie Ridge","s":3744,"la":18.2279,"lo":-77.4205},{"i":62514,"n":"Discovery Bay","s":3744,"la":18.4372,"lo":-77.4181},{"i":62542,"n":"Epworth","s":3744,"la":18.3608,"lo":-77.1334},{"i":62545,"n":"Exchange","s":3744,"la":18.3727,"lo":-77.0657},{"i":62549,"n":"Faith's Pen","s":3744,"la":18.2296,"lo":-77.088},{"i":62583,"n":"Gibraltar","s":3744,"la":18.3508,"lo":-77.4214},{"i":62593,"n":"Golden Grove","s":3744,"la":18.3296,"lo":-77.1226},{"i":62607,"n":"Great Pond","s":3744,"la":18.4023,"lo":-77.0851},{"i":62647,"n":"Higgin Land","s":3744,"la":18.3412,"lo":-77.2707},{"i":62650,"n":"Hinds Town","s":3744,"la":18.3543,"lo":-77.0981},{"i":62662,"n":"Inverness","s":3744,"la":18.2753,"lo":-77.3686},{"i":62710,"n":"Lime Hall","s":3744,"la":18.3974,"lo":-77.2105},{"i":62711,"n":"Lime Tree Gardens","s":3744,"la":18.3454,"lo":-77.3864},{"i":62714,"n":"Linton Park","s":3744,"la":18.2608,"lo":-77.4222},{"i":62737,"n":"Macknie","s":3744,"la":18.2119,"lo":-77.2802},{"i":62738,"n":"Madras","s":3744,"la":18.2911,"lo":-77.4488},{"i":62751,"n":"Mansfield","s":3744,"la":18.4027,"lo":-77.0949},{"i":62783,"n":"Moneague","s":3744,"la":18.2831,"lo":-77.1385},{"i":62798,"n":"Mount Moriah","s":3744,"la":18.2062,"lo":-77.4409},{"i":62803,"n":"Mount Zion","s":3744,"la":18.4338,"lo":-77.2803},{"i":62835,"n":"Ocho Rios","s":3744,"la":18.4076,"lo":-77.1031},{"i":62855,"n":"Parry Town","s":3744,"la":18.3836,"lo":-77.1034},{"i":62881,"n":"Philadelphia","s":3744,"la":18.4001,"lo":-77.3273},{"i":62883,"n":"Pimento Walk","s":3744,"la":18.3958,"lo":-77.1138},{"i":62903,"n":"Priory","s":3744,"la":18.4366,"lo":-77.2455},{"i":62935,"n":"River Head","s":3744,"la":18.2603,"lo":-77.0778},{"i":62959,"n":"Runaway Bay","s":3744,"la":18.4596,"lo":-77.3357},{"i":62962,"n":"Saint Ann’s Bay","s":3744,"la":18.4358,"lo":-77.201},{"i":63019,"n":"St. Ann's Bay","s":3744,"la":18.4299,"lo":-77.2078},{"i":63020,"n":"St. D'Acre","s":3744,"la":18.333,"lo":-77.363},{"i":63029,"n":"Steer Town","s":3744,"la":18.4285,"lo":-77.171},{"i":63037,"n":"Sturge Town","s":3744,"la":18.4163,"lo":-77.3199},{"i":63081,"n":"Walkers Wood","s":3744,"la":18.3194,"lo":-77.0708},{"i":63093,"n":"Watt Town","s":3744,"la":18.2943,"lo":-77.4147},{"i":63126,"n":"York Castle","s":3744,"la":18.2752,"lo":-77.2292},{"i":62292,"n":"Above Rocks","s":3746,"la":18.1143,"lo":-76.8759},{"i":62338,"n":"Bartons","s":3746,"la":18.0289,"lo":-77.1332},{"i":62348,"n":"Bellas Gate","s":3746,"la":18.0471,"lo":-77.1491},{"i":62369,"n":"Bog Walk","s":3746,"la":18.102,"lo":-77.0054},{"i":62372,"n":"Bogwalk","s":3746,"la":18.1047,"lo":-76.9879},{"i":62382,"n":"Braeton","s":3746,"la":17.9417,"lo":-76.8863},{"i":62389,"n":"Bridgeport","s":3746,"la":17.9626,"lo":-76.8781},{"i":62395,"n":"Browns Hill","s":3746,"la":18.0536,"lo":-77.1185},{"i":62436,"n":"Caymanas","s":3746,"la":18.0382,"lo":-76.8983},{"i":62441,"n":"Central Village","s":3746,"la":17.9999,"lo":-76.9239},{"i":62488,"n":"Crescent","s":3746,"la":18.0362,"lo":-76.9763},{"i":62490,"n":"Cromarty","s":3746,"la":17.9584,"lo":-76.9846},{"i":62495,"n":"Cumberland","s":3746,"la":17.9765,"lo":-76.8821},{"i":62532,"n":"Edgewater","s":3746,"la":17.9645,"lo":-76.8655},{"i":62540,"n":"Ensom","s":3746,"la":18.0178,"lo":-76.9622},{"i":62544,"n":"Ewarton","s":3746,"la":18.1833,"lo":-77.0854},{"i":62587,"n":"Ginger Ridge","s":3746,"la":18.0769,"lo":-77.1686},{"i":62589,"n":"Glengoffe","s":3746,"la":18.1521,"lo":-76.8906},{"i":62591,"n":"Golden Acres","s":3746,"la":18.0195,"lo":-76.9804},{"i":62609,"n":"Greater Portmore","s":3746,"la":17.9523,"lo":-76.9113},{"i":62612,"n":"Greendale","s":3746,"la":18.0125,"lo":-76.9483},{"i":62616,"n":"Gregory Park","s":3746,"la":17.9949,"lo":-76.883},{"i":62628,"n":"Hampton Green","s":3746,"la":18.0054,"lo":-76.9682},{"i":62631,"n":"Harewood","s":3746,"la":18.1728,"lo":-76.944},{"i":62632,"n":"Harkers Hall","s":3746,"la":18.1315,"lo":-76.9135},{"i":62643,"n":"Hellshire","s":3746,"la":17.8967,"lo":-76.9619},{"i":62660,"n":"Independence City","s":3746,"la":17.9778,"lo":-76.875},{"i":62689,"n":"Keystone","s":3746,"la":18.0165,"lo":-76.9352},{"i":62696,"n":"Kitson Town","s":3746,"la":18.0349,"lo":-77.0403},{"i":62713,"n":"Linstead","s":3746,"la":18.1368,"lo":-77.0317},{"i":62722,"n":"Lluidas Vale","s":3746,"la":18.1498,"lo":-77.1685},{"i":62808,"n":"Naggo Head","s":3746,"la":17.9642,"lo":-76.8882},{"i":62838,"n":"Old Harbour","s":3746,"la":17.9414,"lo":-77.109},{"i":62839,"n":"Old Harbour Bay","s":3746,"la":17.9092,"lo":-77.0972},{"i":62840,"n":"Old Harbour Road","s":3746,"la":17.958,"lo":-77.0273},{"i":62860,"n":"Part of Guys Hill","s":3746,"la":18.2452,"lo":-76.9908},{"i":62862,"n":"Part of Keystone","s":3746,"la":18.0397,"lo":-76.9511},{"i":62863,"n":"Part of Rock Hall","s":3746,"la":18.0912,"lo":-76.888},{"i":62865,"n":"Passage Fort","s":3746,"la":17.9779,"lo":-76.8679},{"i":62870,"n":"Pear Tree Grove","s":3746,"la":18.2251,"lo":-76.9529},{"i":62888,"n":"Point Hill","s":3746,"la":18.0936,"lo":-77.1048},{"i":62898,"n":"Portmore","s":3746,"la":17.9503,"lo":-76.8821},{"i":62920,"n":"Redwood","s":3746,"la":18.2103,"lo":-76.9854},{"i":62937,"n":"Riversdale","s":3746,"la":18.178,"lo":-76.9664},{"i":62995,"n":"Sligoville","s":3746,"la":18.082,"lo":-76.9399},{"i":63007,"n":"Spanish Town","s":3746,"la":17.9911,"lo":-76.9574},{"i":63008,"n":"Spanish Town Central","s":3746,"la":17.9801,"lo":-76.9229},{"i":63021,"n":"St. John's East","s":3746,"la":18.0009,"lo":-76.9747},{"i":63022,"n":"St. John's West","s":3746,"la":18.0054,"lo":-77.0075},{"i":63066,"n":"Troja","s":3746,"la":18.2049,"lo":-76.932},{"i":63089,"n":"Waterford","s":3746,"la":17.9934,"lo":-76.8609},{"i":63091,"n":"Watermount","s":3746,"la":18.0669,"lo":-77.0911},{"i":63095,"n":"West Cumberland","s":3746,"la":17.9789,"lo":-76.8866},{"i":63108,"n":"Willowdene","s":3746,"la":17.9919,"lo":-76.982},{"i":62290,"n":"Aberdeen","s":3743,"la":18.2051,"lo":-77.6793},{"i":62293,"n":"Accompong","s":3743,"la":18.2298,"lo":-77.7482},{"i":62303,"n":"Alligator Pond","s":3743,"la":17.8693,"lo":-77.5677},{"i":62326,"n":"Balaclava","s":3743,"la":18.1723,"lo":-77.6437},{"i":62328,"n":"Ballards  Valley","s":3743,"la":17.8795,"lo":-77.6309},{"i":62333,"n":"Barbary Hall","s":3743,"la":17.968,"lo":-77.7796},{"i":62360,"n":"Bigwoods","s":3743,"la":17.9334,"lo":-77.719},{"i":62363,"n":"Black River","s":3743,"la":18.0264,"lo":-77.8487},{"i":62371,"n":"Bogue","s":3743,"la":18.1362,"lo":-77.6697},{"i":62381,"n":"Braes River","s":3743,"la":18.0935,"lo":-77.6649},{"i":62390,"n":"Brighton","s":3743,"la":18.1484,"lo":-77.856},{"i":62393,"n":"Brompton","s":3743,"la":18.0679,"lo":-77.8882},{"i":62401,"n":"Bull Savanna","s":3743,"la":17.8868,"lo":-77.5902},{"i":62402,"n":"Bull Savannah","s":3743,"la":17.8806,"lo":-77.59},{"i":62405,"n":"Burnt Savannah","s":3743,"la":18.0318,"lo":-77.7494},{"i":62419,"n":"Carisbrook","s":3743,"la":18.1474,"lo":-77.7737},{"i":62483,"n":"Cotterwood","s":3743,"la":18.0949,"lo":-77.9155},{"i":62487,"n":"Crawford","s":3743,"la":18.0506,"lo":-77.916},{"i":62534,"n":"Elderslie","s":3743,"la":18.2242,"lo":-77.7938},{"i":62577,"n":"Fullerswood","s":3743,"la":18.0153,"lo":-77.7757},{"i":62584,"n":"Giddy Hall","s":3743,"la":18.097,"lo":-77.8676},{"i":62586,"n":"Ginger Hill","s":3743,"la":18.1918,"lo":-77.8487},{"i":62599,"n":"Goshen","s":3743,"la":18.0496,"lo":-77.6414},{"i":62651,"n":"Holland","s":3743,"la":18.1036,"lo":-77.8016},{"i":62655,"n":"Hopeton","s":3743,"la":17.9563,"lo":-77.6624},{"i":62682,"n":"Junction","s":3743,"la":17.9147,"lo":-77.5989},{"i":62699,"n":"Lacovia","s":3743,"la":18.0884,"lo":-77.7535},{"i":62705,"n":"Leeds","s":3743,"la":18.014,"lo":-77.6837},{"i":62717,"n":"Lititz","s":3743,"la":17.9403,"lo":-77.5951},{"i":62739,"n":"Maggotty","s":3743,"la":18.1734,"lo":-77.7668},{"i":62743,"n":"Malvern","s":3743,"la":17.9667,"lo":-77.7},{"i":62770,"n":"Merrywood","s":3743,"la":18.2179,"lo":-77.8377},{"i":62771,"n":"Middle Quarters","s":3743,"la":18.1146,"lo":-77.8381},{"i":62805,"n":"Mountainside","s":3743,"la":17.9808,"lo":-77.7479},{"i":62806,"n":"Mulgrave","s":3743,"la":18.2116,"lo":-77.8202},{"i":62807,"n":"Myersville","s":3743,"la":17.997,"lo":-77.6243},{"i":62809,"n":"Nain","s":3743,"la":17.9653,"lo":-77.6053},{"i":62818,"n":"New Market","s":3743,"la":18.1536,"lo":-77.9096},{"i":62823,"n":"Newell","s":3743,"la":17.921,"lo":-77.7465},{"i":62826,"n":"Newton","s":3743,"la":18.1109,"lo":-77.7235},{"i":62854,"n":"Parottee","s":3743,"la":17.9617,"lo":-77.8177},{"i":62872,"n":"Pedro Plains","s":3743,"la":17.8857,"lo":-77.7134},{"i":62877,"n":"Pepper","s":3743,"la":18.021,"lo":-77.6128},{"i":62884,"n":"Pisgah","s":3743,"la":18.196,"lo":-77.8867},{"i":62889,"n":"Pondside","s":3743,"la":17.9815,"lo":-77.7945},{"i":62902,"n":"Potsdam","s":3743,"la":17.9187,"lo":-77.6687},{"i":62909,"n":"Quick Step","s":3743,"la":18.2328,"lo":-77.6783},{"i":62915,"n":"Red Bank","s":3743,"la":17.9378,"lo":-77.6258},{"i":62923,"n":"Retirement","s":3743,"la":18.2074,"lo":-77.767},{"i":62951,"n":"Rose Hall","s":3743,"la":17.9265,"lo":-77.6415},{"i":62960,"n":"Russels","s":3743,"la":17.9864,"lo":-77.6506},{"i":62971,"n":"Santa Cruz","s":3743,"la":18.0534,"lo":-77.6984},{"i":62976,"n":"Scholefield","s":3743,"la":18.0237,"lo":-77.7188},{"i":62993,"n":"Siloah","s":3743,"la":18.1633,"lo":-77.7106},{"i":62996,"n":"Slipe","s":3743,"la":18.0574,"lo":-77.7969},{"i":63004,"n":"Southfield","s":3743,"la":17.8821,"lo":-77.6699},{"i":63017,"n":"Springfield","s":3743,"la":18.1766,"lo":-77.8739},{"i":63049,"n":"Thornton","s":3743,"la":18.1956,"lo":-77.7225},{"i":63054,"n":"Top Hill","s":3743,"la":17.8932,"lo":-77.6379},{"i":63062,"n":"Treasure Beach","s":3743,"la":17.8955,"lo":-77.7605},{"i":63083,"n":"Warminister","s":3743,"la":17.9624,"lo":-77.6396},{"i":63086,"n":"Watchwell","s":3743,"la":17.9388,"lo":-77.7725},{"i":63100,"n":"White Hill","s":3743,"la":18.1565,"lo":-77.8107},{"i":62294,"n":"Adelphi","s":3745,"la":18.4506,"lo":-77.7859},{"i":62298,"n":"Albion","s":3745,"la":18.4847,"lo":-77.9141},{"i":62312,"n":"Anchovy","s":3745,"la":18.4103,"lo":-77.9317},{"i":62315,"n":"Arcadia","s":3745,"la":18.2499,"lo":-77.7923},{"i":62337,"n":"Barrett Town","s":3745,"la":18.5087,"lo":-77.7963},{"i":62358,"n":"Bickersteth","s":3745,"la":18.3634,"lo":-77.9365},{"i":62370,"n":"Bogue","s":3745,"la":18.4372,"lo":-77.9202},{"i":62386,"n":"Brandon Hill","s":3745,"la":18.4777,"lo":-77.9112},{"i":62415,"n":"Cambridge","s":3745,"la":18.3131,"lo":-77.8955},{"i":62418,"n":"Canterbury","s":3745,"la":18.4792,"lo":-77.9166},{"i":62429,"n":"Catadupa","s":3745,"la":18.2805,"lo":-77.8658},{"i":62430,"n":"Catherine Hall","s":3745,"la":18.4626,"lo":-77.9229},{"i":62431,"n":"Catherine Mount","s":3745,"la":18.4567,"lo":-77.8969},{"i":62469,"n":"Comfort Hall","s":3745,"la":18.4127,"lo":-77.9181},{"i":62480,"n":"Coral Gardens","s":3745,"la":18.5079,"lo":-77.8803},{"i":62481,"n":"Cornwall","s":3745,"la":18.4893,"lo":-77.8102},{"i":62516,"n":"Down Town Montego Bay","s":3745,"la":18.4773,"lo":-77.9203},{"i":62525,"n":"Dumfries","s":3745,"la":18.4297,"lo":-77.7559},{"i":62546,"n":"Fairfield","s":3745,"la":18.4508,"lo":-77.9124},{"i":62551,"n":"Farm Heights","s":3745,"la":18.4687,"lo":-77.8776},{"i":62555,"n":"Flagstaff","s":3745,"la":18.3541,"lo":-77.7713},{"i":62556,"n":"Flamstead","s":3745,"la":18.3141,"lo":-77.8132},{"i":62557,"n":"Flankers","s":3745,"la":18.5026,"lo":-77.9083},{"i":62560,"n":"Flower Hill","s":3745,"la":18.4843,"lo":-77.8391},{"i":62572,"n":"Friendship","s":3745,"la":18.4459,"lo":-77.8624},{"i":62579,"n":"Garlands","s":3745,"la":18.2781,"lo":-77.7891},{"i":62588,"n":"Glendevon","s":3745,"la":18.4849,"lo":-77.8971},{"i":62597,"n":"Goodwill","s":3745,"la":18.4695,"lo":-77.7565},{"i":62604,"n":"Granville","s":3745,"la":18.4419,"lo":-77.894},{"i":62611,"n":"Green Pond","s":3745,"la":18.4736,"lo":-77.8778},{"i":62615,"n":"Greenwood","s":3745,"la":18.4977,"lo":-77.7524},{"i":62656,"n":"Hopeton","s":3745,"la":18.3986,"lo":-77.8683},{"i":62664,"n":"Ironshore","s":3745,"la":18.5132,"lo":-77.8511},{"i":62665,"n":"Irwin","s":3745,"la":18.4495,"lo":-77.8772},{"i":62675,"n":"John's Hall","s":3745,"la":18.4285,"lo":-77.8501},{"i":62709,"n":"Lilliput","s":3745,"la":18.5059,"lo":-77.7769},{"i":62730,"n":"Lottery","s":3745,"la":18.415,"lo":-77.807},{"i":62742,"n":"Maldon","s":3745,"la":18.3383,"lo":-77.81},{"i":62754,"n":"Maroon Town","s":3745,"la":18.3446,"lo":-77.7954},{"i":62779,"n":"Mocho","s":3745,"la":18.2914,"lo":-77.8258},{"i":62784,"n":"Montego Bay","s":3745,"la":18.4712,"lo":-77.9188},{"i":62785,"n":"Montego Hill","s":3745,"la":18.4804,"lo":-77.8815},{"i":62786,"n":"Montpelier","s":3745,"la":18.3761,"lo":-77.9136},{"i":62794,"n":"Mount Carey","s":3745,"la":18.3889,"lo":-77.9437},{"i":62795,"n":"Mount Horeb","s":3745,"la":18.3332,"lo":-77.8667},{"i":62801,"n":"Mount Salem","s":3745,"la":18.466,"lo":-77.9079},{"i":62828,"n":"Niagara","s":3745,"la":18.2653,"lo":-77.8188},{"i":62833,"n":"Norwood","s":3745,"la":18.4922,"lo":-77.8863},{"i":62842,"n":"Orange","s":3745,"la":18.4539,"lo":-77.8278},{"i":62852,"n":"Paradise","s":3745,"la":18.494,"lo":-77.9098},{"i":62885,"n":"Pitfour","s":3745,"la":18.4321,"lo":-77.8901},{"i":62899,"n":"Porto Bello","s":3745,"la":18.4661,"lo":-77.8699},{"i":62914,"n":"Reading","s":3745,"la":18.4372,"lo":-77.9473},{"i":62922,"n":"Retirement","s":3745,"la":18.4374,"lo":-77.88},{"i":62926,"n":"Retrieve","s":3745,"la":18.289,"lo":-77.9008},{"i":62948,"n":"Roehampton","s":3745,"la":18.399,"lo":-77.8993},{"i":62950,"n":"Rose Hall","s":3745,"la":18.5123,"lo":-77.8183},{"i":62952,"n":"Rose Heights","s":3745,"la":18.4694,"lo":-77.8953},{"i":62954,"n":"Rose Mount Garden","s":3745,"la":18.4639,"lo":-77.894},{"i":62956,"n":"Rosemount","s":3745,"la":18.4748,"lo":-77.8922},{"i":62965,"n":"Salt Spring","s":3745,"la":18.4869,"lo":-77.8655},{"i":62985,"n":"Seven Rivers","s":3745,"la":18.347,"lo":-77.9138},{"i":63003,"n":"Somerton","s":3745,"la":18.405,"lo":-77.7707},{"i":63010,"n":"Spot Valley","s":3745,"la":18.4787,"lo":-77.7911},{"i":63032,"n":"Stonehenge","s":3745,"la":18.2423,"lo":-77.8504},{"i":63039,"n":"Summer Hill","s":3745,"la":18.3736,"lo":-77.7935},{"i":63041,"n":"Sunderland","s":3745,"la":18.3979,"lo":-77.8273},{"i":63046,"n":"Tangle River","s":3745,"la":18.3434,"lo":-77.8362},{"i":63057,"n":"Tower Hill/Moy Hall","s":3745,"la":18.4404,"lo":-77.9602},{"i":63070,"n":"Tucker","s":3745,"la":18.449,"lo":-77.8944},{"i":63073,"n":"Unity Hall","s":3745,"la":18.433,"lo":-77.9768},{"i":63075,"n":"Vaughnsfield","s":3745,"la":18.3213,"lo":-77.7805},{"i":63094,"n":"Welcome Hall","s":3745,"la":18.369,"lo":-77.8367},{"i":63097,"n":"West Green","s":3745,"la":18.4624,"lo":-77.9176},{"i":62309,"n":"Amiel Town","s":3747,"la":18.3403,"lo":-76.9761},{"i":62313,"n":"Annotto Bay","s":3747,"la":18.2717,"lo":-76.7652},{"i":62325,"n":"Baileys Vale","s":3747,"la":18.3453,"lo":-76.9259},{"i":62342,"n":"Baxter Mountain","s":3747,"la":18.204,"lo":-76.772},{"i":62347,"n":"Belfield","s":3747,"la":18.2735,"lo":-76.8357},{"i":62375,"n":"Bonnygate","s":3747,"la":18.3287,"lo":-76.9461},{"i":62383,"n":"Brainerd","s":3747,"la":18.1699,"lo":-76.8689},{"i":62392,"n":"Broadgate","s":3747,"la":18.2285,"lo":-76.8079},{"i":62414,"n":"Camberwell","s":3747,"la":18.2393,"lo":-76.7809},{"i":62421,"n":"Carron Hall","s":3747,"la":18.278,"lo":-76.9525},{"i":62428,"n":"Castleton","s":3747,"la":18.1762,"lo":-76.7834},{"i":62448,"n":"Charles Town","s":3747,"la":18.3892,"lo":-77.0398},{"i":62459,"n":"Clonmel","s":3747,"la":18.2428,"lo":-76.8314},{"i":62511,"n":"Devon Pen","s":3747,"la":18.2156,"lo":-76.8244},{"i":62515,"n":"Dover","s":3747,"la":18.2553,"lo":-76.7081},{"i":62539,"n":"Enfield","s":3747,"la":18.2204,"lo":-76.7374},{"i":62541,"n":"Epson","s":3747,"la":18.2522,"lo":-76.7264},{"i":62559,"n":"Flint River","s":3747,"la":18.2379,"lo":-76.9217},{"i":62568,"n":"Free Hill","s":3747,"la":18.3544,"lo":-76.9432},{"i":62573,"n":"Friendship Gap","s":3747,"la":18.1972,"lo":-76.8196},{"i":62578,"n":"Galina","s":3747,"la":18.4027,"lo":-76.9004},{"i":62580,"n":"Gayle","s":3747,"la":18.3428,"lo":-77.0021},{"i":62619,"n":"Guys Hill","s":3747,"la":18.2624,"lo":-76.9956},{"i":62626,"n":"Hampstead","s":3747,"la":18.3205,"lo":-76.9048},{"i":62648,"n":"Highgate","s":3747,"la":18.2774,"lo":-76.8955},{"i":62666,"n":"Islington","s":3747,"la":18.3216,"lo":-76.841},{"i":62668,"n":"Jacks River","s":3747,"la":18.3722,"lo":-76.941},{"i":62671,"n":"Jeffery Town","s":3747,"la":18.2896,"lo":-77.0034},{"i":62698,"n":"Labyrinth","s":3747,"la":18.3442,"lo":-77.0323},{"i":62725,"n":"Long Road","s":3747,"la":18.2134,"lo":-76.7501},{"i":62734,"n":"Lucky Hill","s":3747,"la":18.3025,"lo":-77.0168},{"i":62747,"n":"Mango Valley","s":3747,"la":18.3748,"lo":-76.9769},{"i":62756,"n":"Martin","s":3747,"la":18.3012,"lo":-76.8726},{"i":62760,"n":"Mason Hall","s":3747,"la":18.3966,"lo":-76.9206},{"i":62774,"n":"Mile Gully","s":3747,"la":18.318,"lo":-76.9605},{"i":62841,"n":"Oracabessa","s":3747,"la":18.4032,"lo":-76.9464},{"i":62893,"n":"Port Maria","s":3747,"la":18.3685,"lo":-76.8895},{"i":62906,"n":"Prospect","s":3747,"la":18.4127,"lo":-77.0412},{"i":62924,"n":"Retreat","s":3747,"la":18.3787,"lo":-77.0159},{"i":62928,"n":"Richmond","s":3747,"la":18.2111,"lo":-76.883},{"i":62940,"n":"Robins Bay","s":3747,"la":18.3124,"lo":-76.8178},{"i":62967,"n":"Sandside","s":3747,"la":18.3389,"lo":-76.8955},{"i":62977,"n":"Scotts Hall","s":3747,"la":18.1908,"lo":-76.8394},{"i":63121,"n":"Woodpark","s":3747,"la":18.2973,"lo":-76.9811},{"i":63122,"n":"Woodside","s":3747,"la":18.2526,"lo":-76.9268},{"i":62296,"n":"Airy Castle","s":3750,"la":17.9251,"lo":-76.3422},{"i":62299,"n":"Albion","s":3750,"la":17.9012,"lo":-76.6076},{"i":62311,"n":"Amity Hall","s":3750,"la":17.9676,"lo":-76.257},{"i":62314,"n":"Arcadia","s":3750,"la":17.9223,"lo":-76.3003},{"i":62332,"n":"Baptist","s":3750,"la":17.8767,"lo":-76.5784},{"i":62335,"n":"Barking Lodge","s":3750,"la":17.8928,"lo":-76.2892},{"i":62339,"n":"Bath","s":3750,"la":17.9482,"lo":-76.3492},{"i":62355,"n":"Bethel","s":3750,"la":17.9853,"lo":-76.5805},{"i":62438,"n":"Cedar Valley","s":3750,"la":18.0282,"lo":-76.5956},{"i":62455,"n":"Church Corner","s":3750,"la":17.8872,"lo":-76.419},{"i":62500,"n":"Dalvey","s":3750,"la":17.9024,"lo":-76.25},{"i":62502,"n":"Danvers Pen","s":3750,"la":17.9288,"lo":-76.4759},{"i":62522,"n":"Duckenfield","s":3750,"la":17.922,"lo":-76.2266},{"i":62524,"n":"Duhaney Pen","s":3750,"la":17.894,"lo":-76.4319},{"i":62529,"n":"Easington","s":3750,"la":17.924,"lo":-76.5882},{"i":62535,"n":"Eleven Miles","s":3750,"la":17.9374,"lo":-76.6434},{"i":62561,"n":"Font Hill","s":3750,"la":17.9406,"lo":-76.5117},{"i":62592,"n":"Golden Grove","s":3750,"la":17.9336,"lo":-76.2725},{"i":62622,"n":"Hagley Gap","s":3750,"la":18.0484,"lo":-76.6278},{"i":62627,"n":"Hampton Court","s":3750,"la":17.9178,"lo":-76.2613},{"i":62639,"n":"Hayfield","s":3750,"la":17.982,"lo":-76.3684},{"i":62649,"n":"Hillside","s":3750,"la":17.9962,"lo":-76.4908},{"i":62677,"n":"Johns Town","s":3750,"la":17.8966,"lo":-76.3614},{"i":62678,"n":"Johnson Mountain","s":3750,"la":17.9809,"lo":-76.3199},{"i":62680,"n":"Jones Pen","s":3750,"la":17.9507,"lo":-76.5477},{"i":62706,"n":"Leith Hall","s":3750,"la":17.8797,"lo":-76.3433},{"i":62719,"n":"Llandewey","s":3750,"la":17.9448,"lo":-76.6225},{"i":62721,"n":"Lloyds","s":3750,"la":17.915,"lo":-76.5409},{"i":62735,"n":"Lyssons","s":3750,"la":17.8871,"lo":-76.3796},{"i":62772,"n":"Middleton","s":3750,"la":17.9397,"lo":-76.4356},{"i":62789,"n":"Morant Bay","s":3750,"la":17.8815,"lo":-76.4093},{"i":62797,"n":"Mount Lebanus","s":3750,"la":17.9754,"lo":-76.5389},{"i":62820,"n":"New Monkland","s":3750,"la":17.9916,"lo":-76.5733},{"i":62850,"n":"Pamphret","s":3750,"la":17.8757,"lo":-76.5174},{"i":62869,"n":"Pear Tree","s":3750,"la":17.9116,"lo":-76.3168},{"i":62891,"n":"Poormans Corner","s":3750,"la":17.8915,"lo":-76.5835},{"i":62894,"n":"Port Morant","s":3750,"la":17.8995,"lo":-76.3429},{"i":62907,"n":"Prospect","s":3750,"la":17.874,"lo":-76.3496},{"i":62912,"n":"Ramble","s":3750,"la":17.9679,"lo":-76.6263},{"i":62925,"n":"Retreat","s":3750,"la":17.8776,"lo":-76.3679},{"i":62932,"n":"Richmond Vale","s":3750,"la":17.9744,"lo":-76.5904},{"i":62936,"n":"River Head","s":3750,"la":17.9924,"lo":-76.6108},{"i":62957,"n":"Rowlandsfield","s":3750,"la":17.9735,"lo":-76.2878},{"i":62980,"n":"Seaforth","s":3750,"la":17.9442,"lo":-76.4566},{"i":63001,"n":"Somerset","s":3750,"la":18.0098,"lo":-76.546},{"i":63011,"n":"Spring Bank","s":3750,"la":17.9599,"lo":-76.326},{"i":63012,"n":"Spring Garden","s":3750,"la":17.9175,"lo":-76.4298},{"i":63042,"n":"Sunning Hill","s":3750,"la":17.9561,"lo":-76.4093},{"i":63064,"n":"Trinity Ville","s":3750,"la":17.9608,"lo":-76.5143},{"i":63065,"n":"Trinityville","s":3750,"la":17.9572,"lo":-76.4942},{"i":63098,"n":"Wheelerfield","s":3750,"la":17.9587,"lo":-76.2962},{"i":63099,"n":"White Hall","s":3750,"la":17.998,"lo":-76.431},{"i":63101,"n":"White Horses","s":3750,"la":17.8962,"lo":-76.4708},{"i":63109,"n":"Wilmington","s":3750,"la":17.9286,"lo":-76.3896},{"i":63112,"n":"Winchester","s":3750,"la":17.9418,"lo":-76.2982},{"i":63124,"n":"Yallahs","s":3750,"la":17.8748,"lo":-76.5624},{"i":63125,"n":"York","s":3750,"la":17.9285,"lo":-76.4398},{"i":62297,"n":"Albert Town","s":3755,"la":18.2943,"lo":-77.5424},{"i":62306,"n":"Alps","s":3755,"la":18.355,"lo":-77.509},{"i":62379,"n":"Bounty Hall","s":3755,"la":18.458,"lo":-77.7166},{"i":62384,"n":"Brampton","s":3755,"la":18.4426,"lo":-77.4642},{"i":62403,"n":"Bunkers Hill","s":3755,"la":18.362,"lo":-77.6861},{"i":62457,"n":"Clarks Town","s":3755,"la":18.4224,"lo":-77.5333},{"i":62501,"n":"Daniel Town","s":3755,"la":18.464,"lo":-77.6159},{"i":62505,"n":"Deeside","s":3755,"la":18.3598,"lo":-77.7372},{"i":62521,"n":"Duanvale","s":3755,"la":18.4027,"lo":-77.5961},{"i":62526,"n":"Duncans","s":3755,"la":18.468,"lo":-77.5363},{"i":62550,"n":"Falmouth","s":3755,"la":18.4936,"lo":-77.6559},{"i":62569,"n":"Freemans Hall","s":3755,"la":18.2838,"lo":-77.5018},{"i":62605,"n":"Granville","s":3755,"la":18.4505,"lo":-77.6885},{"i":62625,"n":"Hampden","s":3755,"la":18.4422,"lo":-77.732},{"i":62669,"n":"Jackson Town","s":3755,"la":18.4178,"lo":-77.4846},{"i":62674,"n":"Joe Hut","s":3755,"la":18.2674,"lo":-77.4962},{"i":62694,"n":"Kinloss","s":3755,"la":18.3964,"lo":-77.5697},{"i":62729,"n":"Lorrimers","s":3755,"la":18.2303,"lo":-77.4921},{"i":62755,"n":"Martha Brae","s":3755,"la":18.4696,"lo":-77.6591},{"i":62878,"n":"Perth Town","s":3755,"la":18.4311,"lo":-77.6258},{"i":62921,"n":"Refuge","s":3755,"la":18.451,"lo":-77.5775},{"i":62933,"n":"Rio Bueno","s":3755,"la":18.4641,"lo":-77.4804},{"i":62963,"n":"Salt Marsh","s":3755,"la":18.4842,"lo":-77.7118},{"i":62966,"n":"Samuels Prospect","s":3755,"la":18.451,"lo":-77.5144},{"i":62975,"n":"Sawyers","s":3755,"la":18.3788,"lo":-77.4969},{"i":62988,"n":"Sherwood Content","s":3755,"la":18.3823,"lo":-77.6364},{"i":63009,"n":"Spicy Hill","s":3755,"la":18.4576,"lo":-77.5475},{"i":63013,"n":"Spring Garden","s":3755,"la":18.2937,"lo":-77.567},{"i":63027,"n":"St. Vincent","s":3755,"la":18.3342,"lo":-77.5479},{"i":63030,"n":"Stettin","s":3755,"la":18.2822,"lo":-77.5409},{"i":63031,"n":"Stewart Town","s":3755,"la":18.3989,"lo":-77.4519},{"i":63068,"n":"Troy","s":3755,"la":18.2492,"lo":-77.6098},{"i":63072,"n":"Ulster Spring","s":3755,"la":18.3211,"lo":-77.4968},{"i":63078,"n":"Wait-A-Bit","s":3755,"la":18.2533,"lo":-77.5084},{"i":63079,"n":"Wakefield","s":3755,"la":18.4146,"lo":-77.7091},{"i":63084,"n":"Warsop","s":3755,"la":18.2618,"lo":-77.5677},{"i":63110,"n":"Wilson's Run","s":3755,"la":18.2847,"lo":-77.6932},{"i":63116,"n":"Wirefence","s":3755,"la":18.2531,"lo":-77.5328},{"i":62289,"n":"12th Street","s":3742,"la":18.211,"lo":-78.136},{"i":62310,"n":"Amity","s":3742,"la":18.2736,"lo":-77.898},{"i":62320,"n":"Ashton","s":3742,"la":18.2314,"lo":-77.9207},{"i":62336,"n":"Barneyside","s":3742,"la":18.2767,"lo":-77.9696},{"i":62340,"n":"Bath","s":3742,"la":18.2573,"lo":-78.1175},{"i":62341,"n":"Bath Mountain","s":3742,"la":18.3443,"lo":-78.0993},{"i":62343,"n":"Beaufort","s":3742,"la":18.2342,"lo":-77.9501},{"i":62346,"n":"Beeston Spring","s":3742,"la":18.1601,"lo":-77.9754},{"i":62350,"n":"Belvedere","s":3742,"la":18.2522,"lo":-77.9321},{"i":62353,"n":"Berkshire","s":3742,"la":18.2129,"lo":-77.9037},{"i":62356,"n":"Bethel Town","s":3742,"la":18.295,"lo":-77.9511},{"i":62359,"n":"Big Bridge","s":3742,"la":18.2332,"lo":-78.1672},{"i":62367,"n":"Bluefields","s":3742,"la":18.166,"lo":-78.027},{"i":62368,"n":"Bog","s":3742,"la":18.1563,"lo":-77.9436},{"i":62394,"n":"Broughton","s":3742,"la":18.2175,"lo":-78.2289},{"i":62404,"n":"Burnt Savannah","s":3742,"la":18.3168,"lo":-78.1263},{"i":62411,"n":"Cairn Curran","s":3742,"la":18.2284,"lo":-78.0113},{"i":62413,"n":"Caledonia","s":3742,"la":18.2587,"lo":-78.0117},{"i":62420,"n":"Carmel","s":3742,"la":18.1733,"lo":-77.9393},{"i":62434,"n":"Cave","s":3742,"la":18.2102,"lo":-78.0407},{"i":62445,"n":"Chantilly","s":3742,"la":18.2306,"lo":-78.1246},{"i":62475,"n":"Content","s":3742,"la":18.1829,"lo":-77.9992},{"i":62482,"n":"Cornwall Mountian","s":3742,"la":18.2872,"lo":-77.9867},{"i":62503,"n":"Darliston","s":3742,"la":18.2373,"lo":-77.9763},{"i":62508,"n":"Delveland","s":3742,"la":18.2971,"lo":-78.2396},{"i":62513,"n":"Dillion Bigwoods","s":3742,"la":18.2094,"lo":-77.9908},{"i":62527,"n":"Dundee","s":3742,"la":18.2368,"lo":-77.887},{"i":62538,"n":"Enfield","s":3742,"la":18.214,"lo":-77.9527},{"i":62553,"n":"Ferris","s":3742,"la":18.2227,"lo":-78.0559},{"i":62564,"n":"Fort Williams","s":3742,"la":18.2983,"lo":-78.0633},{"i":62574,"n":"Frome","s":3742,"la":18.2797,"lo":-78.149},{"i":62576,"n":"Fullersfield","s":3742,"la":18.2989,"lo":-78.1998},{"i":62582,"n":"Georges Plain","s":3742,"la":18.2765,"lo":-78.1312},{"i":62596,"n":"Gooden's River","s":3742,"la":18.2422,"lo":-78.1284},{"i":62600,"n":"Grange","s":3742,"la":18.3316,"lo":-78.0804},{"i":62601,"n":"Grange Hill","s":3742,"la":18.3308,"lo":-78.184},{"i":62621,"n":"Haddo","s":3742,"la":18.2861,"lo":-78.0189},{"i":62634,"n":"Harmony Town","s":3742,"la":18.2199,"lo":-78.1369},{"i":62645,"n":"Hertford","s":3742,"la":18.2718,"lo":-78.0908},{"i":62673,"n":"Jerusalem","s":3742,"la":18.3246,"lo":-78.2156},{"i":62688,"n":"Kentucky","s":3742,"la":18.1993,"lo":-78.0177},{"i":62690,"n":"Kilmarnoch","s":3742,"la":18.1241,"lo":-77.9277},{"i":62700,"n":"Lambs River","s":3742,"la":18.2682,"lo":-77.9141},{"i":62704,"n":"Leamington","s":3742,"la":18.2135,"lo":-77.9274},{"i":62707,"n":"Lenox Bigwoods","s":3742,"la":18.2139,"lo":-77.9721},{"i":62718,"n":"Little London","s":3742,"la":18.2452,"lo":-78.2265},{"i":62720,"n":"Llandilo","s":3742,"la":18.2344,"lo":-78.1389},{"i":62736,"n":"Mackfield","s":3742,"la":18.3116,"lo":-78.0247},{"i":62768,"n":"Mearnsville","s":3742,"la":18.1886,"lo":-78.0287},{"i":62792,"n":"Mount Airy","s":3742,"la":18.2474,"lo":-78.3228},{"i":62802,"n":"Mount Stewart","s":3742,"la":18.3041,"lo":-77.9927},{"i":62811,"n":"Negril","s":3742,"la":18.2684,"lo":-78.3481},{"i":62819,"n":"New Market Oval","s":3742,"la":18.2137,"lo":-78.1381},{"i":62821,"n":"New Roads","s":3742,"la":18.1912,"lo":-77.9361},{"i":62822,"n":"New Works","s":3742,"la":18.1725,"lo":-77.9664},{"i":62845,"n":"Orange Hill","s":3742,"la":18.2342,"lo":-78.3028},{"i":62868,"n":"Paul Island","s":3742,"la":18.272,"lo":-78.1861},{"i":62879,"n":"Petersfield","s":3742,"la":18.2659,"lo":-78.0576},{"i":62880,"n":"Petersville","s":3742,"la":18.137,"lo":-77.9505},{"i":62896,"n":"Porters Mountain","s":3742,"la":18.3291,"lo":-78.0491},{"i":62916,"n":"Red Hills","s":3742,"la":18.3055,"lo":-78.1128},{"i":62927,"n":"Revival","s":3742,"la":18.2426,"lo":-78.2844},{"i":62939,"n":"Roaring River","s":3742,"la":18.3012,"lo":-78.0432},{"i":62961,"n":"Russia","s":3742,"la":18.2165,"lo":-78.1236},{"i":62973,"n":"Savanna-la-Mar","s":3742,"la":18.2189,"lo":-78.1332},{"i":62974,"n":"Savannah-la-mar Business Dist.","s":3742,"la":18.2196,"lo":-78.1303},{"i":62979,"n":"Seaford Town","s":3742,"la":18.2434,"lo":-77.905},{"i":62981,"n":"Seaton Crescent","s":3742,"la":18.2168,"lo":-78.136},{"i":62987,"n":"Shefield","s":3742,"la":18.2841,"lo":-78.2917},{"i":62991,"n":"Shoalin Grotto","s":3742,"la":18.2206,"lo":-78.1402},{"i":62997,"n":"Smithfield","s":3742,"la":18.2228,"lo":-78.0879},{"i":63023,"n":"St. Leonards","s":3742,"la":18.2553,"lo":-77.8889},{"i":63034,"n":"Strathbogie","s":3742,"la":18.2386,"lo":-78.1171},{"i":63035,"n":"Strawberry","s":3742,"la":18.3068,"lo":-78.0894},{"i":63036,"n":"Struie","s":3742,"la":18.2532,"lo":-77.9566},{"i":63050,"n":"Three Mile River","s":3742,"la":18.2571,"lo":-78.1428},{"i":63058,"n":"Town Head","s":3742,"la":18.339,"lo":-78.1357},{"i":63069,"n":"Truro","s":3742,"la":18.313,"lo":-78.1549},{"i":63088,"n":"Water Works","s":3742,"la":18.2332,"lo":-78.043},{"i":63103,"n":"Whitehouse","s":3742,"la":18.1028,"lo":-77.957},{"i":63105,"n":"Whithorn","s":3742,"la":18.2711,"lo":-78.0381},{"i":63106,"n":"Williamsfield","s":3742,"la":18.3339,"lo":-78.0696}]