[{"i":81029,"n":"Arawa","s":4831,"la":-6.2298,"lo":155.566},{"i":81033,"n":"Central Bougainville","s":4831,"la":-6.2281,"lo":155.5658},{"i":81063,"n":"Kieta","s":4831,"la":-6.2146,"lo":155.6325},{"i":81091,"n":"North Bougainville","s":4831,"la":-5.4219,"lo":154.6728},{"i":81097,"n":"Panguna","s":4831,"la":-6.3164,"lo":155.4848},{"i":81109,"n":"South Bougainville","s":4831,"la":-6.7459,"lo":155.6964},{"i":81024,"n":"Abau","s":4847,"la":-10.0833,"lo":148.9167},{"i":81041,"n":"Goilala","s":4847,"la":-8.3333,"lo":147},{"i":81055,"n":"Kairuku-Hiri","s":4847,"la":-9.1365,"lo":147.2791},{"i":81104,"n":"Rigo","s":4847,"la":-9.75,"lo":147.8333},{"i":81034,"n":"Chuave","s":4846,"la":-6.1667,"lo":145.0833},{"i":81043,"n":"Gumine","s":4846,"la":-6.25,"lo":144.8833},{"i":81059,"n":"Karimui Nomane","s":4846,"la":-6.5833,"lo":144.8333},{"i":81062,"n":"Kerowagi","s":4846,"la":-5.9333,"lo":144.8833},{"i":81073,"n":"Kundiawa","s":4846,"la":-5.9167,"lo":145.05},{"i":81107,"n":"Sinasina Yonggamugl","s":4846,"la":-6.0833,"lo":145.0167},{"i":81040,"n":"Gazelle","s":4834,"la":-4.4833,"lo":151.8667},{"i":81069,"n":"Kokopo","s":4834,"la":-4.4,"lo":152.2833},{"i":81098,"n":"Pomio","s":4834,"la":-5.5,"lo":151.3333},{"i":81102,"n":"Rabaul","s":4834,"la":-4.1833,"lo":152.1667},{"i":81036,"n":"Daulo","s":4845,"la":-5.9833,"lo":145.2333},{"i":81042,"n":"Goroka","s":4845,"la":-6.05,"lo":145.3833},{"i":81045,"n":"Henganofi","s":4845,"la":-6.2167,"lo":145.6667},{"i":81054,"n":"Kainantu","s":4845,"la":-6.4167,"lo":145.9167},{"i":81077,"n":"Lufa","s":4845,"la":-6.45,"lo":145.25},{"i":81095,"n":"Obura Wonenara","s":4845,"la":-6.5543,"lo":145.9733},{"i":81096,"n":"Okapa","s":4845,"la":-6.6333,"lo":145.5},{"i":81118,"n":"Unggai Bena","s":4845,"la":-6.1167,"lo":145.5167},{"i":81056,"n":"Kandep","s":4848,"la":-5.8333,"lo":143.55},{"i":81071,"n":"Kompiam Ambum","s":4848,"la":-5.25,"lo":144},{"i":81075,"n":"Lagaip Porgera","s":4848,"la":-5.3833,"lo":143.1667},{"i":81100,"n":"Porgera","s":4848,"la":-5.463,"lo":143.148},{"i":81122,"n":"Wabag","s":4848,"la":-5.3333,"lo":143.65},{"i":81123,"n":"Wapenamanda","s":4848,"la":-5.6667,"lo":143.9167},{"i":81061,"n":"Kerema","s":4839,"la":-7.796,"lo":146.093},{"i":81064,"n":"Kikori","s":4839,"la":-7.25,"lo":144.3333},{"i":81070,"n":"Komo Margarima","s":4833,"la":-6.1167,"lo":143},{"i":81072,"n":"Koroba-Lake Kopiago","s":4833,"la":-5.4167,"lo":142.5},{"i":81114,"n":"Tari","s":4833,"la":-5.845,"lo":142.9467},{"i":81115,"n":"Tari Pori","s":4833,"la":-6.2833,"lo":142.8333},{"i":81028,"n":"Angalimp South Wahgi","s":4832,"la":-6.05,"lo":144.5667},{"i":81051,"n":"Jimi","s":4832,"la":-5.5333,"lo":144.5667},{"i":81093,"n":"North Wahgi","s":4832,"la":-5.8,"lo":144.6833},{"i":81031,"n":"Bogia","s":4843,"la":-4.5,"lo":145},{"i":81078,"n":"Madang","s":4843,"la":-5.2215,"lo":145.7869},{"i":81084,"n":"Middle Ramu","s":4843,"la":-4.9167,"lo":144.75},{"i":81103,"n":"Rai Coast","s":4843,"la":-5.723,"lo":146.4615},{"i":81111,"n":"Sumkar","s":4843,"la":-4.8,"lo":145.55},{"i":81119,"n":"Usino Bundi","s":4843,"la":-5.5333,"lo":145.1667},{"i":81076,"n":"Lorengau","s":4842,"la":-2.0341,"lo":147.2717},{"i":81079,"n":"Manus","s":4842,"la":-2.0963,"lo":146.9661},{"i":81027,"n":"Alotau","s":4849,"la":-10.25,"lo":150.0833},{"i":81038,"n":"Esa’ala","s":4849,"la":-9.5833,"lo":150.75},{"i":81066,"n":"Kiriwina Goodenough","s":4849,"la":-8.4833,"lo":151.0667},{"i":81105,"n":"Samarai","s":4849,"la":-10.6104,"lo":150.6621},{"i":81106,"n":"Samarai Murua","s":4849,"la":-10.4964,"lo":150.547},{"i":81032,"n":"Bulolo","s":4835,"la":-7.4167,"lo":146.75},{"i":81039,"n":"Finschhafen","s":4835,"la":-6.4167,"lo":147.5},{"i":81046,"n":"Huon Gulf","s":4835,"la":-7.1833,"lo":146.95},{"i":81052,"n":"Kabwum","s":4835,"la":-6.0833,"lo":147},{"i":81074,"n":"Lae","s":4835,"la":-6.5,"lo":146.8333},{"i":81080,"n":"Markham","s":4835,"la":-6.6415,"lo":146.8604},{"i":81082,"n":"Menyamya","s":4835,"la":-7.25,"lo":146.1667},{"i":81089,"n":"Nawae","s":4835,"la":-6.4667,"lo":146.9667},{"i":81117,"n":"Tewai Siassi","s":4835,"la":-6.15,"lo":147.5333},{"i":81124,"n":"Wau","s":4835,"la":-7.3378,"lo":146.7165},{"i":81060,"n":"Kavieng","s":4841,"la":-3,"lo":151.4167},{"i":81087,"n":"Namatanai","s":4841,"la":-4.3333,"lo":152.8333},{"i":81049,"n":"Ijivitari","s":4838,"la":-9.3333,"lo":148.5833},{"i":81068,"n":"Kokoda","s":4838,"la":-8.8778,"lo":147.7364},{"i":81099,"n":"Popondetta","s":4838,"la":-8.7654,"lo":148.2325},{"i":81108,"n":"Sohe","s":4838,"la":-9,"lo":147.9167},{"i":81088,"n":"National Capital District","s":4837,"la":-9.4226,"lo":147.1664},{"i":81101,"n":"Port Moresby","s":4837,"la":-9.4772,"lo":147.1509},{"i":81025,"n":"Aitape","s":4836,"la":-3.137,"lo":142.3491},{"i":81026,"n":"Aitape Lumi","s":4836,"la":-3.25,"lo":142.0833},{"i":81094,"n":"Nuku","s":4836,"la":-3.6667,"lo":142.4167},{"i":81116,"n":"Telefomin","s":4836,"la":-4.9167,"lo":141.6667},{"i":81120,"n":"Vanimo","s":4836,"la":-2.6837,"lo":141.302},{"i":81121,"n":"Vanimo Green","s":4836,"la":-3.3667,"lo":141.35},{"i":81047,"n":"Ialibu","s":4844,"la":-6.2821,"lo":143.9935},{"i":81048,"n":"Ialibu Pangia","s":4844,"la":-6.1667,"lo":144},{"i":81050,"n":"Imbonggu","s":4844,"la":-6.1667,"lo":144},{"i":81053,"n":"Kagua Erave","s":4844,"la":-6.6667,"lo":144},{"i":81081,"n":"Mendi","s":4844,"la":-6.1475,"lo":143.6563},{"i":81090,"n":"Nipa Kutubu","s":4844,"la":-6.3333,"lo":143.3333},{"i":81057,"n":"Kandrian","s":4830,"la":-6.2066,"lo":149.5474},{"i":81058,"n":"Kandrian Gloucester","s":4830,"la":-6.0833,"lo":149.9167},{"i":81065,"n":"Kimbe","s":4830,"la":-5.5508,"lo":150.1377},{"i":81112,"n":"Talasea","s":4830,"la":-5.6667,"lo":149.5833},{"i":81030,"n":"Baiyer Mul","s":4840,"la":-5.5333,"lo":144.15},{"i":81037,"n":"Dei","s":4840,"la":-5.6833,"lo":144.3667},{"i":81044,"n":"Hagen","s":4840,"la":-5.8333,"lo":144.2833},{"i":81086,"n":"Mount Hagen","s":4840,"la":-5.8575,"lo":144.2306},{"i":81113,"n":"Tambul Nebilyer","s":4840,"la":-5.9833,"lo":144.15},{"i":81035,"n":"Daru","s":4850,"la":-9.0779,"lo":143.2089},{"i":81067,"n":"Kiunga","s":4850,"la":-6.1219,"lo":141.2906},{"i":81083,"n":"Middle Fly","s":4850,"la":-7.1667,"lo":142.0333},{"i":81085,"n":"Morehead","s":4850,"la":-8.7106,"lo":141.6367},{"i":81092,"n":"North Fly","s":4850,"la":-5.729,"lo":141.3748},{"i":81110,"n":"South Fly","s":4850,"la":-8.6167,"lo":142.1167}]